Workbook
Name _____xlnm._FilterDatabase: #REF!
Name Print_Titles: #REF!
Name _____xlnm.Print_Titles_1: #REF!
Name ____xlnm._FilterDatabase: #REF!
Name ____xlnm.Print_Titles_1: #REF!
Name ___xlnm._FilterDatabase: #REF!
Name ___xlnm.Print_Titles_1: #REF!
Name __xlnm._FilterDatabase: #REF!
Name __xlnm.Print_Titles_1: #REF!
Name _bce2004: #REF!
Name _BCE2005: #REF!
Name _DAT1: #REF!
Name _DAT10: #REF!
Name _DAT2: #REF!
Name _DAT3: #REF!
Name _DAT4: #REF!
Name _DAT5: #REF!
Name _DAT6: #REF!
Name _DAT7: #REF!
Name _DAT8: #REF!
Name _DAT9: #REF!
Name _sys2005: #REF!
Name a: #REF!
Name AA: #REF!
Name ACT_FIJOS_VALOR: #REF!
Name AJUSTE_REAJ_FIS_AF: #REF!
Name anexo: #REF!
Name anexo04: #REF!
Name Print_Area: #REF!
Name asd: #REF!
Name BSH: #REF!
Name BuiltIn_Print_Area: #REF!
Name BuiltIn_Print_Area___0: #REF!
Name BVAN: #REF!
Name CALDECNM: #REF!
Name Caracter: #REF!
Name CIIU: #REF!
Name CIIUNM: #REF!
Name Citibank: #REF!
Name CLASEDEC: #REF!
Name CLASEDECNM: #REF!
Name COBRANZAS: #REF!
Name CODADMONNM: #REF!
Name CODDOCSNM: #REF!
Name CUENTAS: #REF!
Name DEPTOSNM: #REF!
Name dimension: #REF!
Name DIVIPOL: #REF!
Name DIVIPOL1: #REF!
Name DIVIPOLCOD: #REF!
Name DIVIPOLNM: #REF!
Name Excel_BuiltIn_Print_Titles: #REF!
Name Excel_BuiltIn_Print_Titles_1: #REF!
Name FACTURAS: #REF!
Name G: #REF!
Name gActEcono: #REF!
Name gAdmon: #REF!
Name gAño: #REF!
Name gApe1Dec: #REF!
Name gApe1Rev: #REF!

Sheet Cartera
A1: Cuenta contable | B1: Denominación cuenta contable | C1: Emisor | D1: Tipo | E1: Estado | F1: Grupo | G1: Casa de bolsa | H1: Serie | I1: Fecha Compra | J1: Fecha Vencimiento Serie | K1: Calificacion de riesgo | L1: Instrumento | M1: Tasa Interes | N1: Referencia Tasa | O1: Moneda | P1: Importe Valorizado | Q1: Valor actual en PYG | R1: Valor actual en USD | S1: Estado de cupon / Capital | T1: Comitente | U1: Capital | V1: Intereses | W1: No. Cupón | X1: % Amortizacion | Y1: Amortizacion de capital | Z1: Consolidado | AA1: Titulos Colocados | AB1: Total | AC1: Instrumento | AD1: Instrumento 3 | AE1: Mes Vto | AF1: Año Vto | AG1: Observaciones
A2: 12303 | B2: Acciones en Otras Empresas LP - PYG | C2: SUDAMERIS BANK S.A.E.C.A. | D2: Capital | E2: Activo | F2: Grupo Sudameris | H2: Acciones Ordinarias "A" | I2: 43581 | J2: No aplica | Acciones | K2: AA+py Estable | L2: Acciones | M2: 0.07 | N2: =IF(AND(M2>#REF!,Cartera!O2="Guaraníes"),"Rendimiento significativo",IF(AND(M2>#REF!,Cartera!O2="Dólares americanos"),"Rendimiento significativo","Rendimiento no significativo")) -> #REF! | O2: Guaraníes | P2: 3100000 | Q2: =IF(O2="Guaraníes",P2,P2*#REF!) -> 3100000 | R2: =IF(O2="Guaraníes",P2/#REF!,P2) -> #REF! | S2: Pendiente | AC2: =IF(ISNUMBER(SEARCH("Acciones",L2)),"Acciones",IF(ISNUMBER(SEARCH("Bono",L2)),"Bonos",IF(ISNUMBER(SEARCH("CDA",L2)),"CDA",IF(ISNUMBER(SEARCH("Fondo",L2)),"Fondo",0)))) -> Acciones | AD2: Otros | AE2: =IFERROR((MONTH(J2)),0) -> 0 | AF2: =IFERROR((YEAR(J2)),0) -> 0
A3: Vencido | Cobrado | B3: Vencido | Cobrado | C3: BANCO BASA S.A. | D3: Intereses | E3: Vencido | Cobrado | F3: Grupo Cartes | G3: CAPITAL MARKETS CBSA | H3: PYBAM01F9268 | J3: 44767 | K3: AA-py Estable | L3: Bonos Subordinados | M3: 0.0525 | N3: =IF(AND(M3>#REF!,Cartera!O3="Guaraníes"),"Rendimiento significativo",IF(AND(M3>#REF!,Cartera!O3="Dólares americanos"),"Rendimiento significativo","Rendimiento no significativo")) -> #REF! | O3: Dólares americanos | P3: 174.52055 | Q3: =IF(O3="Guaraníes",P3,P3*#REF!) -> #REF! | R3: =IF(O3="Guaraníes",P3/#REF!,P3) -> 174.52055 | S3: Acreditado | T3: 4 | W3: 1/24 | X3: 0 | Y3: 0 | Z3: 17.452055 | AA3: 10 | AB3: 174.52055 | AC3: =IF(ISNUMBER(SEARCH("Acciones",L3)),"Acciones",IF(ISNUMBER(SEARCH("Bono",L3)),"Bonos",IF(ISNUMBER(SEARCH("CDA",L3)),"CDA",IF(ISNUMBER(SEARCH("Fondo",L3)),"Fondo",0)))) -> Bonos | AD3: Otros | AE3: =IFERROR((MONTH(J3)),0) -> 7 | AF3: =IFERROR((YEAR(J3)),0) -> 2022
A4: Vencido | Cobrado | B4: Vencido | Cobrado | C4: CEMENTOS CONCEPCIÓN SOCIEDAD ANÓNIMA EMISORA | D4: Intereses | E4: Vencido | Cobrado | F4: Grupo Cartes | G4: ASU CAPITAL CBSA | H4: PYCEC01F3409 | I4: 44680 | J4: 44771 | K4: pyAA- Estable | L4: Bonos | M4: 0.06 | N4: =IF(AND(M4>#REF!,Cartera!O4="Guaraníes"),"Rendimiento significativo",IF(AND(M4>#REF!,Cartera!O4="Dólares americanos"),"Rendimiento significativo","Rendimiento no significativo")) -> #REF! | O4: Dólares americanos | P4: 747.95 | Q4: =IF(O4="Guaraníes",P4,P4*#REF!) -> #REF! | R4: =IF(O4="Guaraníes",P4/#REF!,P4) -> 747.95 | S4: Acreditado | T4: 17035 | V4: 14.96 | AA4: 50 | AC4: =IF(ISNUMBER(SEARCH("Acciones",L4)),"Acciones",IF(ISNUMBER(SEARCH("Bono",L4)),"Bonos",IF(ISNUMBER(SEARCH("CDA",L4)),"CDA",IF(ISNUMBER(SEARCH("Fondo",L4)),"Fondo",0)))) -> Bonos | AD4: Otros | AE4: =IFERROR((MONTH(J4)),0) -> 7 | AF4: =IFERROR((YEAR(J4)),0) -> 2022
A5: Vencido | Cobrado | B5: Vencido | Cobrado | C5: CEMENTOS CONCEPCIÓN SOCIEDAD ANÓNIMA EMISORA | D5: Intereses | E5: Vencido | Cobrado | F5: Grupo Cartes | G5: ASU CAPITAL CBSA | H5: PYCEC01F3409 | I5: 44680 | J5: 44862 | K5: pyAA- Estable | L5: Bonos | M5: 0.06 | N5: =IF(AND(M5>#REF!,Cartera!O5="Guaraníes"),"Rendimiento significativo",IF(AND(M5>#REF!,Cartera!O5="Dólares americanos"),"Rendimiento significativo","Rendimiento no significativo")) -> #REF! | O5: Dólares americanos | P5: 747.95 | Q5: =IF(O5="Guaraníes",P5,P5*#REF!) -> #REF! | R5: =IF(O5="Guaraníes",P5/#REF!,P5) -> 747.95 | S5: Acreditado | T5: 17035 | V5: 14.96 | AA5: 50 | AC5: =IF(ISNUMBER(SEARCH("Acciones",L5)),"Acciones",IF(ISNUMBER(SEARCH("Bono",L5)),"Bonos",IF(ISNUMBER(SEARCH("CDA",L5)),"CDA",IF(ISNUMBER(SEARCH("Fondo",L5)),"Fondo",0)))) -> Bonos | AD5: Otros | AE5: =IFERROR((MONTH(J5)),0) -> 10 | AF5: =IFERROR((YEAR(J5)),0) -> 2022
A6: Vencido | Cobrado | B6: Vencido | Cobrado | C6: CEMENTOS CONCEPCIÓN SOCIEDAD ANÓNIMA EMISORA | D6: Intereses | E6: Vencido | Cobrado | F6: Grupo Cartes | G6: ASU CAPITAL CBSA | H6: PYCEC01F3409 | I6: 44680 | J6: 44953 | K6: pyAA- Estable | L6: Bonos | M6: 0.06 | N6: =IF(AND(M6>#REF!,Cartera!O6="Guaraníes"),"Rendimiento significativo",IF(AND(M6>#REF!,Cartera!O6="Dólares americanos"),"Rendimiento significativo","Rendimiento no significativo")) -> #REF! | O6: Dólares americanos | P6: 747.95 | Q6: =IF(O6="Guaraníes",P6,P6*#REF!) -> #REF! | R6: =IF(O6="Guaraníes",P6/#REF!,P6) -> 747.95 | S6: Acreditado | T6: 17035 | V6: 14.96 | AA6: 50 | AC6: =IF(ISNUMBER(SEARCH("Acciones",L6)),"Acciones",IF(ISNUMBER(SEARCH("Bono",L6)),"Bonos",IF(ISNUMBER(SEARCH("CDA",L6)),"CDA",IF(ISNUMBER(SEARCH("Fondo",L6)),"Fondo",0)))) -> Bonos | AD6: Otros | AE6: =IFERROR((MONTH(J6)),0) -> 1 | AF6: =IFERROR((YEAR(J6)),0) -> 2023
A7: Vencido | Cobrado | B7: Vencido | Cobrado | C7: CEMENTOS CONCEPCIÓN SOCIEDAD ANÓNIMA EMISORA | D7: Intereses | E7: Vencido | Cobrado | F7: Grupo Cartes | G7: ASU CAPITAL CBSA | H7: PYCEC01F3409 | I7: 44680 | J7: 45044 | K7: pyAA- Estable | L7: Bonos | M7: 0.06 | N7: =IF(AND(M7>#REF!,Cartera!O7="Guaraníes"),"Rendimiento significativo",IF(AND(M7>#REF!,Cartera!O7="Dólares americanos"),"Rendimiento significativo","Rendimiento no significativo")) -> #REF! | O7: Dólares americanos | P7: 747.95 | Q7: =IF(O7="Guaraníes",P7,P7*#REF!) -> #REF! | R7: =IF(O7="Guaraníes",P7/#REF!,P7) -> 747.95 | S7: Acreditado | T7: 17035 | V7: 14.96 | AA7: 50 | AC7: =IF(ISNUMBER(SEARCH("Acciones",L7)),"Acciones",IF(ISNUMBER(SEARCH("Bono",L7)),"Bonos",IF(ISNUMBER(SEARCH("CDA",L7)),"CDA",IF(ISNUMBER(SEARCH("Fondo",L7)),"Fondo",0)))) -> Bonos | AD7: Otros | AE7: =IFERROR((MONTH(J7)),0) -> 4 | AF7: =IFERROR((YEAR(J7)),0) -> 2023
A8: Vencido | Cobrado | B8: Vencido | Cobrado | C8: CEMENTOS CONCEPCIÓN SOCIEDAD ANÓNIMA EMISORA | D8: Intereses | E8: Vencido | Cobrado | F8: Grupo Cartes | G8: ASU CAPITAL CBSA | H8: PYCEC01F3409 | I8: 44680 | J8: 45135 | K8: pyAA- Estable | L8: Bonos | M8: 0.06 | N8: =IF(AND(M8>#REF!,Cartera!O8="Guaraníes"),"Rendimiento significativo",IF(AND(M8>#REF!,Cartera!O8="Dólares americanos"),"Rendimiento significativo","Rendimiento no significativo")) -> #REF! | O8: Dólares americanos | P8: 747.95 | Q8: =IF(O8="Guaraníes",P8,P8*#REF!) -> #REF! | R8: =IF(O8="Guaraníes",P8/#REF!,P8) -> 747.95 | S8: Acreditado | T8: 17035 | V8: 14.96 | AA8: 50 | AC8: =IF(ISNUMBER(SEARCH("Acciones",L8)),"Acciones",IF(ISNUMBER(SEARCH("Bono",L8)),"Bonos",IF(ISNUMBER(SEARCH("CDA",L8)),"CDA",IF(ISNUMBER(SEARCH("Fondo",L8)),"Fondo",0)))) -> Bonos | AD8: Otros | AE8: =IFERROR((MONTH(J8)),0) -> 7 | AF8: =IFERROR((YEAR(J8)),0) -> 2023
A9: Vencido | Cobrado | B9: Vencido | Cobrado | C9: CEMENTOS CONCEPCIÓN SOCIEDAD ANÓNIMA EMISORA | D9: Intereses | E9: Vencido | Cobrado | F9: Grupo Cartes | G9: ASU CAPITAL CBSA | H9: PYCEC01F3409 | I9: 44680 | J9: 45226 | K9: pyAA- Estable | L9: Bonos | M9: 0.06 | N9: =IF(AND(M9>#REF!,Cartera!O9="Guaraníes"),"Rendimiento significativo",IF(AND(M9>#REF!,Cartera!O9="Dólares americanos"),"Rendimiento significativo","Rendimiento no significativo")) -> #REF! | O9: Dólares americanos | P9: 747.9452 | Q9: =IF(O9="Guaraníes",P9,P9*#REF!) -> #REF! | R9: =IF(O9="Guaraníes",P9/#REF!,P9) -> 747.9452 | S9: Acreditado | T9: 17035 | V9: 14.96 | AA9: 50 | AC9: =IF(ISNUMBER(SEARCH("Acciones",L9)),"Acciones",IF(ISNUMBER(SEARCH("Bono",L9)),"Bonos",IF(ISNUMBER(SEARCH("CDA",L9)),"CDA",IF(ISNUMBER(SEARCH("Fondo",L9)),"Fondo",0)))) -> Bonos | AD9: Otros | AE9: =IFERROR((MONTH(J9)),0) -> 10 | AF9: =IFERROR((YEAR(J9)),0) -> 2023
A10: Vencido | Cobrado | B10: Vencido | Cobrado | C10: CEMENTOS CONCEPCIÓN SOCIEDAD ANÓNIMA EMISORA | D10: Intereses | E10: Vencido | Cobrado | F10: Grupo Cartes | G10: ASU CAPITAL CBSA | H10: PYCEC01F3409 | I10: 44680 | J10: 45317 | K10: pyAA- Estable | L10: Bonos | M10: 0.06 | N10: =IF(AND(M10>#REF!,Cartera!O10="Guaraníes"),"Rendimiento significativo",IF(AND(M10>#REF!,Cartera!O10="Dólares americanos"),"Rendimiento significativo","Rendimiento no significativo")) -> #REF! | O10: Dólares americanos | P10: 747.9452 | Q10: =IF(O10="Guaraníes",P10,P10*#REF!) -> #REF! | R10: =IF(O10="Guaraníes",P10/#REF!,P10) -> 747.9452 | S10: Acreditado | T10: 17035 | V10: 14.96 | AA10: 50 | AC10: =IF(ISNUMBER(SEARCH("Acciones",L10)),"Acciones",IF(ISNUMBER(SEARCH("Bono",L10)),"Bonos",IF(ISNUMBER(SEARCH("CDA",L10)),"CDA",IF(ISNUMBER(SEARCH("Fondo",L10)),"Fondo",0)))) -> Bonos | AD10: Otros | AE10: =IFERROR((MONTH(J10)),0) -> 1 | AF10: =IFERROR((YEAR(J10)),0) -> 2024
A11: Vencido | Cobrado | B11: Vencido | Cobrado | C11: CEMENTOS CONCEPCIÓN SOCIEDAD ANÓNIMA EMISORA | D11: Intereses | E11: Vencido | Cobrado | F11: Grupo Cartes | G11: ASU CAPITAL CBSA | H11: PYCEC01F3409 | I11: 44680 | J11: 45408 | K11: pyAA- Estable | L11: Bonos | M11: 0.06 | N11: =IF(AND(M11>#REF!,Cartera!O11="Guaraníes"),"Rendimiento significativo",IF(AND(M11>#REF!,Cartera!O11="Dólares americanos"),"Rendimiento significativo","Rendimiento no significativo")) -> #REF! | O11: Dólares americanos | P11: 747.9452 | Q11: =IF(O11="Guaraníes",P11,P11*#REF!) -> #REF! | R11: =IF(O11="Guaraníes",P11/#REF!,P11) -> 747.9452 | S11: Acreditado | T11: 17035 | V11: 14.96 | AA11: 50 | AC11: =IF(ISNUMBER(SEARCH("Acciones",L11)),"Acciones",IF(ISNUMBER(SEARCH("Bono",L11)),"Bonos",IF(ISNUMBER(SEARCH("CDA",L11)),"CDA",IF(ISNUMBER(SEARCH("Fondo",L11)),"Fondo",0)))) -> Bonos | AD11: Otros | AE11: =IFERROR((MONTH(J11)),0) -> 4 | AF11: =IFERROR((YEAR(J11)),0) -> 2024
A12: Vencido | Cobrado | B12: Vencido | Cobrado | C12: CEMENTOS CONCEPCIÓN SOCIEDAD ANÓNIMA EMISORA | D12: Intereses | E12: Vencido | Cobrado | F12: Grupo Cartes | G12: ASU CAPITAL CBSA | H12: PYCEC01F3409 | I12: 44680 | J12: 45499 | K12: pyAA- Estable | L12: Bonos | M12: 0.06 | N12: =IF(AND(M12>#REF!,Cartera!O12="Guaraníes"),"Rendimiento significativo",IF(AND(M12>#REF!,Cartera!O12="Dólares americanos"),"Rendimiento significativo","Rendimiento no significativo")) -> #REF! | O12: Dólares americanos | P12: 747.9452 | Q12: =IF(O12="Guaraníes",P12,P12*#REF!) -> #REF! | R12: =IF(O12="Guaraníes",P12/#REF!,P12) -> 747.9452 | S12: Acreditado | T12: 17035 | V12: 14.96 | AA12: 50 | AC12: =IF(ISNUMBER(SEARCH("Acciones",L12)),"Acciones",IF(ISNUMBER(SEARCH("Bono",L12)),"Bonos",IF(ISNUMBER(SEARCH("CDA",L12)),"CDA",IF(ISNUMBER(SEARCH("Fondo",L12)),"Fondo",0)))) -> Bonos | AD12: Otros | AE12: =IFERROR((MONTH(J12)),0) -> 7 | AF12: =IFERROR((YEAR(J12)),0) -> 2024
A13: 11401 | B13: Intereses Financieros a Cobrar CP - USD | C13: BANCO RIO SAECA | D13: Intereses | E13: Activo | F13: Grupo Continental | G13: AVALON CBSA | H13: PYBRO02F1560 | J13: 45425 | K13: A+py Estable | L13: Bonos Subordinados | M13: 0.0525 | N13: =IF(AND(M13>#REF!,Cartera!O141="Guaraníes"),"Rendimiento significativo",IF(AND(M13>#REF!,Cartera!O141="Dólares americanos"),"Rendimiento significativo","Rendimiento no significativo")) -> #REF! | O13: Dólares americanos | P13: 785.34246 | Q13: =IF(O13="Guaraníes",P13,P13*#REF!) -> #REF! | R13: =IF(O13="Guaraníes",P13/#REF!,P13) -> 785.34246 | S13: Pendiente | T13: 8 | W13: / | X13: 0 | Y13: 0 | Z13: 26.178082 | AA13: 30 | AB13: 785.34246 | AC13: =IF(ISNUMBER(SEARCH("Acciones",L13)),"Acciones",IF(ISNUMBER(SEARCH("Bono",L13)),"Bonos",IF(ISNUMBER(SEARCH("CDA",L13)),"CDA",IF(ISNUMBER(SEARCH("Fondo",L13)),"Fondo",0)))) -> Bonos | AD13: Otros | AE13: =IFERROR((MONTH(J13)),0) -> 5 | AF13: =IFERROR((YEAR(J13)),0) -> 2024 | AG13: Acreditado en cuenta del Fondo de Garantia. Se solicitó devolución a la cuenta 677
A14: Vencido | Cobrado | B14: Vencido | Cobrado | C14: RIEDER & CÍA. S.A.C.I. | D14: Intereses | E14: Vencido | Cobrado | F14: No aplica a grupos | G14: VALORES CBSA | H14: PYRIE03F8098 | J14: 45525 | K14: pyBBB- Estable | L14: Bonos | M14: 0.0675 | N14: =IF(AND(M14>#REF!,Cartera!O2376="Guaraníes"),"Rendimiento significativo",IF(AND(M14>#REF!,Cartera!O2376="Dólares americanos"),"Rendimiento significativo","Rendimiento no significativo")) -> #REF! | O14: Dólares americanos | P14: 49.09 | Q14: =IF(O14="Guaraníes",P14,P14*#REF!) -> #REF! | R14: =IF(O14="Guaraníes",P14/#REF!,P14) -> 49.09 | S14: Acreditado | T14: 593 | W14: 4/43 | X14: 4.1666667 | Y14: 41.666667 | Z14: 47.03653 | AA14: 8 | AB14: 376.29224 | AC14: =IF(ISNUMBER(SEARCH("Acciones",L14)),"Acciones",IF(ISNUMBER(SEARCH("Bono",L14)),"Bonos",IF(ISNUMBER(SEARCH("CDA",L14)),"CDA",IF(ISNUMBER(SEARCH("Fondo",L14)),"Fondo",0)))) -> Bonos | AD14: Otros | AE14: =IFERROR((MONTH(J14)),0) -> 8 | AF14: =IFERROR((YEAR(J14)),0) -> 2024
A15: 12315 | B15: Intereses Financieros a Cobrar LP - USD | C15: SOLAR BANCO S.A.E. | D15: Intereses | E15: Activo | F15: No aplica a grupos | G15: CADIEM CBSA | H15: PYSAF01F1422 | J15: 45659 | K15: Apy Estable | L15: Bonos Subordinados | M15: 0.055 | N15: =IF(AND(M15>#REF!,Cartera!O901="Guaraníes"),"Rendimiento significativo",IF(AND(M15>#REF!,Cartera!O901="Dólares americanos"),"Rendimiento significativo","Rendimiento no significativo")) -> #REF! | O15: Dólares americanos | P15: 420.41097 | Q15: =IF(O15="Guaraníes",P15,P15*#REF!) -> #REF! | R15: =IF(O15="Guaraníes",P15/#REF!,P15) -> 420.41097 | S15: Pendiente | T15: 25 | W15: / | X15: 0 | Y15: 0 | Z15: 14.013699 | AA15: 30 | AB15: 420.41 | AC15: =IF(ISNUMBER(SEARCH("Acciones",L15)),"Acciones",IF(ISNUMBER(SEARCH("Bono",L15)),"Bonos",IF(ISNUMBER(SEARCH("CDA",L15)),"CDA",IF(ISNUMBER(SEARCH("Fondo",L15)),"Fondo",0)))) -> Bonos | AD15: Otros | AE15: =IFERROR((MONTH(J15)),0) -> 1 | AF15: =IFERROR((YEAR(J15)),0) -> 2025
A16: 12316 | B16: Intereses Financieros a Cobrar LP - PYG | C16: TU FINANCIERA SAECA | D16: Intereses | E16: Activo | F16: No aplica a grupos | H16: AA8063 | I16: 45013 | J16: 45659 | K16: A-py Estable | L16: CDA | M16: 0.098 | N16: =IF(AND(M16>#REF!,Cartera!O3105="Guaraníes"),"Rendimiento significativo",IF(AND(M16>#REF!,Cartera!O3105="Dólares americanos"),"Rendimiento significativo","Rendimiento no significativo")) -> #REF! | O16: Guaraníes | P16: 4310993 | Q16: =IF(O16="Guaraníes",P16,P16*#REF!) -> 4310993 | R16: =IF(O16="Guaraníes",P16/#REF!,P16) -> #REF! | S16: Pendiente | AC16: =IF(ISNUMBER(SEARCH("Acciones",L16)),"Acciones",IF(ISNUMBER(SEARCH("Bono",L16)),"Bonos",IF(ISNUMBER(SEARCH("CDA",L16)),"CDA",IF(ISNUMBER(SEARCH("Fondo",L16)),"Fondo",0)))) -> CDA | AD16: Otros | AE16: =IFERROR((MONTH(J16)),0) -> 1 | AF16: =IFERROR((YEAR(J16)),0) -> 2025
A17: 12316 | B17: Intereses Financieros a Cobrar LP - PYG | C17: SOLAR BANCO S.A.E. | D17: Intereses | E17: Activo | F17: No aplica a grupos | H17: 1093 | J17: 45667 | K17: Apy Estable | L17: CDA | M17: 0.065 | N17: =IF(AND(M17>#REF!,Cartera!O2944="Guaraníes"),"Rendimiento significativo",IF(AND(M17>#REF!,Cartera!O2944="Dólares americanos"),"Rendimiento significativo","Rendimiento no significativo")) -> #REF! | O17: Guaraníes | P17: 3134247 | Q17: =IF(O17="Guaraníes",P17,P17*#REF!) -> 3134247 | R17: =IF(O17="Guaraníes",P17/#REF!,P17) -> #REF! | S17: Pendiente | V17: 3134247 | W17: 13/17 | AC17: =IF(ISNUMBER(SEARCH("Acciones",L17)),"Acciones",IF(ISNUMBER(SEARCH("Bono",L17)),"Bonos",IF(ISNUMBER(SEARCH("CDA",L17)),"CDA",IF(ISNUMBER(SEARCH("Fondo",L17)),"Fondo",0)))) -> CDA | AD17: Otros | AE17: =IFERROR((MONTH(J17)),0) -> 1 | AF17: =IFERROR((YEAR(J17)),0) -> 2025
A18: 12315 | B18: Intereses Financieros a Cobrar LP - USD | C18: BANCO RIO SAECA | D18: Intereses | E18: Activo | F18: No aplica a grupos | H18: UH1802 | I18: 45393 | J18: 45669 | K18: A+py Estable | L18: CDA | M18: 0.055 | N18: =IF(AND(M18>#REF!,Cartera!O3574="Guaraníes"),"Rendimiento significativo",IF(AND(M18>#REF!,Cartera!O3574="Dólares americanos"),"Rendimiento significativo","Rendimiento no significativo")) -> #REF! | O18: Dólares americanos | P18: 291.12 | Q18: =IF(O18="Guaraníes",P18,P18*#REF!) -> #REF! | R18: =IF(O18="Guaraníes",P18/#REF!,P18) -> 291.12 | S18: Pendiente | AC18: =IF(ISNUMBER(SEARCH("Acciones",L18)),"Acciones",IF(ISNUMBER(SEARCH("Bono",L18)),"Bonos",IF(ISNUMBER(SEARCH("CDA",L18)),"CDA",IF(ISNUMBER(SEARCH("Fondo",L18)),"Fondo",0)))) -> CDA | AD18: Otros | AE18: =IFERROR((MONTH(J18)),0) -> 1 | AF18: =IFERROR((YEAR(J18)),0) -> 2025
A19: 12315 | B19: Intereses Financieros a Cobrar LP - USD | C19: ENEX PARAGUAY S.A.E. | D19: Intereses | E19: Activo | F19: No aplica a grupos | G19: BASA CBSA | H19: PYENE01F2836 | J19: 45673 | K19: AA+py Estable | L19: Bonos | M19: 0.06 | N19: =IF(AND(M19>#REF!,Cartera!O263="Guaraníes"),"Rendimiento significativo",IF(AND(M19>#REF!,Cartera!O263="Dólares americanos"),"Rendimiento significativo","Rendimiento no significativo")) -> #REF! | O19: Dólares americanos | P19: 747.9452 | Q19: =IF(O19="Guaraníes",P19,P19*#REF!) -> #REF! | R19: =IF(O19="Guaraníes",P19/#REF!,P19) -> 747.9452 | S19: Pendiente | T19: 10834 | W19: 12/28 | X19: 0 | Y19: 0 | Z19: 14.958904 | AA19: 50 | AB19: 747.9452 | AC19: =IF(ISNUMBER(SEARCH("Acciones",L19)),"Acciones",IF(ISNUMBER(SEARCH("Bono",L19)),"Bonos",IF(ISNUMBER(SEARCH("CDA",L19)),"CDA",IF(ISNUMBER(SEARCH("Fondo",L19)),"Fondo",0)))) -> Bonos | AD19: Otros | AE19: =IFERROR((MONTH(J19)),0) -> 1 | AF19: =IFERROR((YEAR(J19)),0) -> 2025
A20: 12315 | B20: Intereses Financieros a Cobrar LP - USD | C20: UENO HOLDING S.A.E.C.A. | D20: Intereses | E20: Activo | F20: Grupo Vazquez | G20: PUENTE CBSA | H20: PYLCR05F9125 | J20: 45673 | K20: pyBBB + Sensible (-) | L20: Bonos | M20: 0.08 | N20: =IF(AND(M20>#REF!,Cartera!O1864="Guaraníes"),"Rendimiento significativo",IF(AND(M20>#REF!,Cartera!O1864="Dólares americanos"),"Rendimiento significativo","Rendimiento no significativo")) -> #REF! | O20: Dólares americanos | P20: 299.17808 | Q20: =IF(O20="Guaraníes",P20,P20*#REF!) -> #REF! | R20: =IF(O20="Guaraníes",P20/#REF!,P20) -> 299.17808 | S20: Pendiente | T20: 3253 | W20: / | X20: 0 | Y20: 0 | Z20: 19.945205 | AA20: 15 | AB20: 299.17807 | AC20: =IF(ISNUMBER(SEARCH("Acciones",L20)),"Acciones",IF(ISNUMBER(SEARCH("Bono",L20)),"Bonos",IF(ISNUMBER(SEARCH("CDA",L20)),"CDA",IF(ISNUMBER(SEARCH("Fondo",L20)),"Fondo",0)))) -> Bonos | AD20: Otros | AE20: =IFERROR((MONTH(J20)),0) -> 1 | AF20: =IFERROR((YEAR(J20)),0) -> 2025
A21: 12316 | B21: Intereses Financieros a Cobrar LP - PYG | C21: SUDAMERIS BANK S.A.E.C.A. | D21: Intereses | E21: Activo | F21: Grupo Sudameris | H21: 86 | I21: 45043 | J21: 45673 | K21: AA+py Estable | L21: CDA | M21: 0.09 | N21: =IF(AND(M21>#REF!,Cartera!O3186="Guaraníes"),"Rendimiento significativo",IF(AND(M21>#REF!,Cartera!O3186="Dólares americanos"),"Rendimiento significativo","Rendimiento no significativo")) -> #REF! | O21: Guaraníes | P21: 11095890 | Q21: =IF(O21="Guaraníes",P21,P21*#REF!) -> 11095890 | R21: =IF(O21="Guaraníes",P21/#REF!,P21) -> #REF! | S21: Pendiente | AC21: =IF(ISNUMBER(SEARCH("Acciones",L21)),"Acciones",IF(ISNUMBER(SEARCH("Bono",L21)),"Bonos",IF(ISNUMBER(SEARCH("CDA",L21)),"CDA",IF(ISNUMBER(SEARCH("Fondo",L21)),"Fondo",0)))) -> CDA | AD21: Otros | AE21: =IFERROR((MONTH(J21)),0) -> 1 | AF21: =IFERROR((YEAR(J21)),0) -> 2025
A22: 12316 | B22: Intereses Financieros a Cobrar LP - PYG | C22: FINANCIERA PARAGUAYO JAPONESA S.A.E.C.A. | D22: Intereses | E22: Activo | F22: No aplica a grupos | H22: AB 6272 | I22: 45404 | J22: 45674 | K22: A-py Fuerte (+) | L22: CDA | M22: 0.085 | N22: =IF(AND(M22>#REF!,Cartera!O3588="Guaraníes"),"Rendimiento significativo",IF(AND(M22>#REF!,Cartera!O3588="Dólares americanos"),"Rendimiento significativo","Rendimiento no significativo")) -> #REF! | O22: Guaraníes | P22: 4191781 | Q22: =IF(O22="Guaraníes",P22,P22*#REF!) -> 4191781 | R22: =IF(O22="Guaraníes",P22/#REF!,P22) -> #REF! | S22: Pendiente | AC22: =IF(ISNUMBER(SEARCH("Acciones",L22)),"Acciones",IF(ISNUMBER(SEARCH("Bono",L22)),"Bonos",IF(ISNUMBER(SEARCH("CDA",L22)),"CDA",IF(ISNUMBER(SEARCH("Fondo",L22)),"Fondo",0)))) -> CDA | AD22: Otros | AE22: =IFERROR((MONTH(J22)),0) -> 1 | AF22: =IFERROR((YEAR(J22)),0) -> 2025
A23: 12315 | B23: Intereses Financieros a Cobrar LP - USD | C23: BANCO BASA S.A. | D23: Intereses | E23: Activo | F23: Grupo Cartes | G23: CAPITAL MARKETS CBSA | H23: PYBAM01F9268 | J23: 45677 | K23: AA-py Estable | L23: Bonos Subordinados | M23: 0.0525 | N23: =IF(AND(M23>#REF!,Cartera!O1133="Guaraníes"),"Rendimiento significativo",IF(AND(M23>#REF!,Cartera!O1133="Dólares americanos"),"Rendimiento significativo","Rendimiento no significativo")) -> #REF! | O23: Dólares americanos | P23: 174.52055 | Q23: =IF(O23="Guaraníes",P23,P23*#REF!) -> #REF! | R23: =IF(O23="Guaraníes",P23/#REF!,P23) -> 174.52055 | S23: Pendiente | T23: 4 | W23: 4/24 | X23: 0 | Y23: 0 | Z23: 17.452055 | AA23: 10 | AB23: 174.52055 | AC23: =IF(ISNUMBER(SEARCH("Acciones",L23)),"Acciones",IF(ISNUMBER(SEARCH("Bono",L23)),"Bonos",IF(ISNUMBER(SEARCH("CDA",L23)),"CDA",IF(ISNUMBER(SEARCH("Fondo",L23)),"Fondo",0)))) -> Bonos | AD23: Otros | AE23: =IFERROR((MONTH(J23)),0) -> 1 | AF23: =IFERROR((YEAR(J23)),0) -> 2025
A24: 12315 | B24: Intereses Financieros a Cobrar LP - USD | C24: BANCO BASA S.A. | D24: Intereses | E24: Activo | F24: Grupo Cartes | G24: BASA CBSA | H24: PYBAM01F9268 | J24: 45677 | K24: AA-py Estable | L24: Bonos Subordinados | M24: 0.07 | N24: =IF(AND(M24>#REF!,Cartera!O3111="Guaraníes"),"Rendimiento significativo",IF(AND(M24>#REF!,Cartera!O3111="Dólares americanos"),"Rendimiento significativo","Rendimiento no significativo")) -> #REF! | O24: Dólares americanos | P24: 872.6 | Q24: =IF(O24="Guaraníes",P24,P24*#REF!) -> #REF! | R24: =IF(O24="Guaraníes",P24/#REF!,P24) -> 872.6 | S24: Pendiente | T24: 10834 | AC24: =IF(ISNUMBER(SEARCH("Acciones",L24)),"Acciones",IF(ISNUMBER(SEARCH("Bono",L24)),"Bonos",IF(ISNUMBER(SEARCH("CDA",L24)),"CDA",IF(ISNUMBER(SEARCH("Fondo",L24)),"Fondo",0)))) -> Bonos | AD24: Otros | AE24: =IFERROR((MONTH(J24)),0) -> 1 | AF24: =IFERROR((YEAR(J24)),0) -> 2025
A25: 12302 | B25: Inversiones en Bonos LP - USD | C25: CEMENTOS CONCEPCIÓN SOCIEDAD ANÓNIMA EMISORA | D25: Capital | E25: Activo | F25: Grupo Cartes | G25: ASU CAPITAL CBSA | H25: PYCEC01F3409 | I25: 44680 | J25: 46864 | K25: pyAA- Estable | L25: Bonos | M25: 0.06 | N25: =IF(AND(M25>#REF!,Cartera!O25="Guaraníes"),"Rendimiento significativo",IF(AND(M25>#REF!,Cartera!O25="Dólares americanos"),"Rendimiento significativo","Rendimiento no significativo")) -> #REF! | O25: Dólares americanos | P25: 50000 | Q25: =IF(O25="Guaraníes",P25,P25*#REF!) -> #REF! | R25: =IF(O25="Guaraníes",P25/#REF!,P25) -> 50000 | S25: Pendiente | T25: 17035 | V25: 14.96 | AA25: 50 | AC25: =IF(ISNUMBER(SEARCH("Acciones",L25)),"Acciones",IF(ISNUMBER(SEARCH("Bono",L25)),"Bonos",IF(ISNUMBER(SEARCH("CDA",L25)),"CDA",IF(ISNUMBER(SEARCH("Fondo",L25)),"Fondo",0)))) -> Bonos | AD25: Otros | AE25: =IFERROR((MONTH(J25)),0) -> 4 | AF25: =IFERROR((YEAR(J25)),0) -> 2028
A26: Vencido | Cobrado | B26: Vencido | Cobrado | C26: MINISTERIO DE HACIENDA | D26: Intereses | E26: Vencido | Cobrado | F26: Instrumentos Públicos | G26: ASU CAPITAL CBSA | H26: PYTNA01F8541 | I26: 44691 | J26: 44732 | K26: Bonos del Tesoro | L26: Bonos del Tesoro | M26: 0.0775 | N26: =IF(AND(M26>#REF!,Cartera!O26="Guaraníes"),"Rendimiento significativo",IF(AND(M26>#REF!,Cartera!O26="Dólares americanos"),"Rendimiento significativo","Rendimiento no significativo")) -> #REF! | O26: Guaraníes | P26: 11625000 | Q26: =IF(O26="Guaraníes",P26,P26*#REF!) -> 11625000 | R26: =IF(O26="Guaraníes",P26/#REF!,P26) -> #REF! | S26: Acreditado | V26: 38750 | AA26: 300 | AC26: =IF(ISNUMBER(SEARCH("Acciones",L26)),"Acciones",IF(ISNUMBER(SEARCH("Bono",L26)),"Bonos",IF(ISNUMBER(SEARCH("CDA",L26)),"CDA",IF(ISNUMBER(SEARCH("Fondo",L26)),"Fondo",0)))) -> Bonos | AD26: Otros | AE26: =IFERROR((MONTH(J26)),0) -> 6 | AF26: =IFERROR((YEAR(J26)),0) -> 2022
A27: Vencido | Cobrado | B27: Vencido | Cobrado | C27: MINISTERIO DE HACIENDA | D27: Intereses | E27: Vencido | Cobrado | F27: Instrumentos Públicos | G27: ASU CAPITAL CBSA | H27: PYTNA01F8541 | I27: 44691 | J27: 44915 | K27: Bonos del Tesoro | L27: Bonos del Tesoro | M27: 0.0775 | N27: =IF(AND(M27>#REF!,Cartera!O27="Guaraníes"),"Rendimiento significativo",IF(AND(M27>#REF!,Cartera!O27="Dólares americanos"),"Rendimiento significativo","Rendimiento no significativo")) -> #REF! | O27: Guaraníes | P27: 11625000 | Q27: =IF(O27="Guaraníes",P27,P27*#REF!) -> 11625000 | R27: =IF(O27="Guaraníes",P27/#REF!,P27) -> #REF! | S27: Acreditado | V27: 38750 | AA27: 300 | AC27: =IF(ISNUMBER(SEARCH("Acciones",L27)),"Acciones",IF(ISNUMBER(SEARCH("Bono",L27)),"Bonos",IF(ISNUMBER(SEARCH("CDA",L27)),"CDA",IF(ISNUMBER(SEARCH("Fondo",L27)),"Fondo",0)))) -> Bonos | AD27: Otros | AE27: =IFERROR((MONTH(J27)),0) -> 12 | AF27: =IFERROR((YEAR(J27)),0) -> 2022
A28: Vencido | Cobrado | B28: Vencido | Cobrado | C28: MINISTERIO DE HACIENDA | D28: Intereses | E28: Vencido | Cobrado | F28: Instrumentos Públicos | G28: ASU CAPITAL CBSA | H28: PYTNA01F8541 | I28: 44691 | J28: 45097 | K28: Bonos del Tesoro | L28: Bonos del Tesoro | M28: 0.0775 | N28: =IF(AND(M28>#REF!,Cartera!O28="Guaraníes"),"Rendimiento significativo",IF(AND(M28>#REF!,Cartera!O28="Dólares americanos"),"Rendimiento significativo","Rendimiento no significativo")) -> #REF! | O28: Guaraníes | P28: 11625000 | Q28: =IF(O28="Guaraníes",P28,P28*#REF!) -> 11625000 | R28: =IF(O28="Guaraníes",P28/#REF!,P28) -> #REF! | S28: Acreditado | V28: 38750 | AA28: 300 | AC28: =IF(ISNUMBER(SEARCH("Acciones",L28)),"Acciones",IF(ISNUMBER(SEARCH("Bono",L28)),"Bonos",IF(ISNUMBER(SEARCH("CDA",L28)),"CDA",IF(ISNUMBER(SEARCH("Fondo",L28)),"Fondo",0)))) -> Bonos | AD28: Otros | AE28: =IFERROR((MONTH(J28)),0) -> 6 | AF28: =IFERROR((YEAR(J28)),0) -> 2023
A29: Vencido | Cobrado | B29: Vencido | Cobrado | C29: MINISTERIO DE HACIENDA | D29: Intereses | E29: Vencido | Cobrado | F29: Instrumentos Públicos | G29: ASU CAPITAL CBSA | H29: PYTNA01F8541 | I29: 44691 | J29: 45280 | K29: Bonos del Tesoro | L29: Bonos del Tesoro | M29: 0.0775 | N29: =IF(AND(M29>#REF!,Cartera!O29="Guaraníes"),"Rendimiento significativo",IF(AND(M29>#REF!,Cartera!O29="Dólares americanos"),"Rendimiento significativo","Rendimiento no significativo")) -> #REF! | O29: Guaraníes | P29: 11625000 | Q29: =IF(O29="Guaraníes",P29,P29*#REF!) -> 11625000 | R29: =IF(O29="Guaraníes",P29/#REF!,P29) -> #REF! | S29: Acreditado | V29: 38750 | AA29: 300 | AC29: =IF(ISNUMBER(SEARCH("Acciones",L29)),"Acciones",IF(ISNUMBER(SEARCH("Bono",L29)),"Bonos",IF(ISNUMBER(SEARCH("CDA",L29)),"CDA",IF(ISNUMBER(SEARCH("Fondo",L29)),"Fondo",0)))) -> Bonos | AD29: Otros | AE29: =IFERROR((MONTH(J29)),0) -> 12 | AF29: =IFERROR((YEAR(J29)),0) -> 2023
A30: Vencido | Cobrado | B30: Vencido | Cobrado | C30: MINISTERIO DE HACIENDA | D30: Intereses | E30: Vencido | Cobrado | F30: Instrumentos Públicos | G30: ASU CAPITAL CBSA | H30: PYTNA01F8541 | I30: 44691 | J30: 45463 | K30: Bonos del Tesoro | L30: Bonos del Tesoro | M30: 0.0775 | N30: =IF(AND(M30>#REF!,Cartera!O30="Guaraníes"),"Rendimiento significativo",IF(AND(M30>#REF!,Cartera!O30="Dólares americanos"),"Rendimiento significativo","Rendimiento no significativo")) -> #REF! | O30: Guaraníes | P30: 11625000 | Q30: =IF(O30="Guaraníes",P30,P30*#REF!) -> 11625000 | R30: =IF(O30="Guaraníes",P30/#REF!,P30) -> #REF! | S30: Acreditado | V30: 38750 | AA30: 300 | AC30: =IF(ISNUMBER(SEARCH("Acciones",L30)),"Acciones",IF(ISNUMBER(SEARCH("Bono",L30)),"Bonos",IF(ISNUMBER(SEARCH("CDA",L30)),"CDA",IF(ISNUMBER(SEARCH("Fondo",L30)),"Fondo",0)))) -> Bonos | AD30: Otros | AE30: =IFERROR((MONTH(J30)),0) -> 6 | AF30: =IFERROR((YEAR(J30)),0) -> 2024
A31: Vencido | Cobrado | B31: Vencido | Cobrado | C31: BANCO FAMILIAR S.A.E.C.A. | D31: Intereses | E31: Vencido | Cobrado | F31: No aplica a grupos | G31: FAMILIAR CBSA | H31: PYFAM10F6756 | I31: 45266 | J31: 45630 | K31: A+py Estable | L31: Bonos Financieros | M31: 0.0795 | N31: =IF(AND(M31>#REF!,Cartera!O3523="Guaraníes"),"Rendimiento significativo",IF(AND(M31>#REF!,Cartera!O3523="Dólares americanos"),"Rendimiento significativo","Rendimiento no significativo")) -> #REF! | O31: Guaraníes | P31: 1982054.8 | Q31: =IF(O31="Guaraníes",P31,P31*#REF!) -> 1982054.8 | R31: =IF(O31="Guaraníes",P31/#REF!,P31) -> #REF! | S31: Acreditado | T31: 26543 | AC31: =IF(ISNUMBER(SEARCH("Acciones",L31)),"Acciones",IF(ISNUMBER(SEARCH("Bono",L31)),"Bonos",IF(ISNUMBER(SEARCH("CDA",L31)),"CDA",IF(ISNUMBER(SEARCH("Fondo",L31)),"Fondo",0)))) -> Bonos | AD31: Otros | AE31: =IFERROR((MONTH(J31)),0) -> 12 | AF31: =IFERROR((YEAR(J31)),0) -> 2024
A32: 12301 | B32: Inversiones en Bonos LP - PYG | C32: MINISTERIO DE HACIENDA | D32: Capital | E32: Activo | F32: Instrumentos Públicos | G32: ASU CAPITAL CBSA | H32: PYTNA01F8541 | I32: 44691 | J32: 45828 | K32: Bonos del Tesoro | L32: Bonos del Tesoro | M32: 0.0775 | N32: =IF(AND(M32>#REF!,Cartera!O32="Guaraníes"),"Rendimiento significativo",IF(AND(M32>#REF!,Cartera!O32="Dólares americanos"),"Rendimiento significativo","Rendimiento no significativo")) -> #REF! | O32: Guaraníes | P32: 300000000 | Q32: =IF(O32="Guaraníes",P32,P32*#REF!) -> 300000000 | R32: =IF(O32="Guaraníes",P32/#REF!,P32) -> #REF! | S32: Pendiente | V32: 38750 | AA32: 300 | AC32: =IF(ISNUMBER(SEARCH("Acciones",L32)),"Acciones",IF(ISNUMBER(SEARCH("Bono",L32)),"Bonos",IF(ISNUMBER(SEARCH("CDA",L32)),"CDA",IF(ISNUMBER(SEARCH("Fondo",L32)),"Fondo",0)))) -> Bonos | AD32: Otros | AE32: =IFERROR((MONTH(J32)),0) -> 6 | AF32: =IFERROR((YEAR(J32)),0) -> 2025
A33: Vencido | Cobrado | B33: Vencido | Cobrado | C33: BANCO BASA S.A. | D33: Intereses | E33: Vencido | Cobrado | F33: Grupo Cartes | G33: ASU CAPITAL CBSA | H33: PYBAM02F3500 | I33: 44704 | J33: 44795 | K33: AA-py Estable | L33: Bonos | M33: 0.06 | N33: =IF(AND(M33>#REF!,Cartera!O33="Guaraníes"),"Rendimiento significativo",IF(AND(M33>#REF!,Cartera!O33="Dólares americanos"),"Rendimiento significativo","Rendimiento no significativo")) -> #REF! | O33: Dólares americanos | P33: 373.9726 | Q33: =IF(O33="Guaraníes",P33,P33*#REF!) -> #REF! | R33: =IF(O33="Guaraníes",P33/#REF!,P33) -> 373.9726 | S33: Acreditado | V33: 14.958904 | AA33: 25 | AC33: =IF(ISNUMBER(SEARCH("Acciones",L33)),"Acciones",IF(ISNUMBER(SEARCH("Bono",L33)),"Bonos",IF(ISNUMBER(SEARCH("CDA",L33)),"CDA",IF(ISNUMBER(SEARCH("Fondo",L33)),"Fondo",0)))) -> Bonos | AD33: Otros | AE33: =IFERROR((MONTH(J33)),0) -> 8 | AF33: =IFERROR((YEAR(J33)),0) -> 2022
A34: Vencido | Cobrado | B34: Vencido | Cobrado | C34: BANCO BASA S.A. | D34: Intereses | E34: Vencido | Cobrado | F34: Grupo Cartes | G34: ASU CAPITAL CBSA | H34: PYBAM02F3500 | I34: 44704 | J34: 44886 | K34: AA-py Estable | L34: Bonos | M34: 0.06 | N34: =IF(AND(M34>#REF!,Cartera!O34="Guaraníes"),"Rendimiento significativo",IF(AND(M34>#REF!,Cartera!O34="Dólares americanos"),"Rendimiento significativo","Rendimiento no significativo")) -> #REF! | O34: Dólares americanos | P34: 373.9726 | Q34: =IF(O34="Guaraníes",P34,P34*#REF!) -> #REF! | R34: =IF(O34="Guaraníes",P34/#REF!,P34) -> 373.9726 | S34: Acreditado | V34: 14.958904 | AA34: 25 | AC34: =IF(ISNUMBER(SEARCH("Acciones",L34)),"Acciones",IF(ISNUMBER(SEARCH("Bono",L34)),"Bonos",IF(ISNUMBER(SEARCH("CDA",L34)),"CDA",IF(ISNUMBER(SEARCH("Fondo",L34)),"Fondo",0)))) -> Bonos | AD34: Otros | AE34: =IFERROR((MONTH(J34)),0) -> 11 | AF34: =IFERROR((YEAR(J34)),0) -> 2022
A35: Vencido | Cobrado | B35: Vencido | Cobrado | C35: BANCO BASA S.A. | D35: Intereses | E35: Vencido | Cobrado | F35: Grupo Cartes | G35: ASU CAPITAL CBSA | H35: PYBAM02F3500 | I35: 44704 | J35: 44977 | K35: AA-py Estable | L35: Bonos | M35: 0.06 | N35: =IF(AND(M35>#REF!,Cartera!O35="Guaraníes"),"Rendimiento significativo",IF(AND(M35>#REF!,Cartera!O35="Dólares americanos"),"Rendimiento significativo","Rendimiento no significativo")) -> #REF! | O35: Dólares americanos | P35: 373.9726 | Q35: =IF(O35="Guaraníes",P35,P35*#REF!) -> #REF! | R35: =IF(O35="Guaraníes",P35/#REF!,P35) -> 373.9726 | S35: Acreditado | V35: 14.958904 | AA35: 25 | AC35: =IF(ISNUMBER(SEARCH("Acciones",L35)),"Acciones",IF(ISNUMBER(SEARCH("Bono",L35)),"Bonos",IF(ISNUMBER(SEARCH("CDA",L35)),"CDA",IF(ISNUMBER(SEARCH("Fondo",L35)),"Fondo",0)))) -> Bonos | AD35: Otros | AE35: =IFERROR((MONTH(J35)),0) -> 2 | AF35: =IFERROR((YEAR(J35)),0) -> 2023
A36: Vencido | Cobrado | B36: Vencido | Cobrado | C36: BANCO BASA S.A. | D36: Intereses | E36: Vencido | Cobrado | F36: Grupo Cartes | G36: ASU CAPITAL CBSA | H36: PYBAM02F3500 | I36: 44704 | J36: 45068 | K36: AA-py Estable | L36: Bonos | M36: 0.06 | N36: =IF(AND(M36>#REF!,Cartera!O36="Guaraníes"),"Rendimiento significativo",IF(AND(M36>#REF!,Cartera!O36="Dólares americanos"),"Rendimiento significativo","Rendimiento no significativo")) -> #REF! | O36: Dólares americanos | P36: 373.9726 | Q36: =IF(O36="Guaraníes",P36,P36*#REF!) -> #REF! | R36: =IF(O36="Guaraníes",P36/#REF!,P36) -> 373.9726 | S36: Acreditado | V36: 14.958904 | AA36: 25 | AC36: =IF(ISNUMBER(SEARCH("Acciones",L36)),"Acciones",IF(ISNUMBER(SEARCH("Bono",L36)),"Bonos",IF(ISNUMBER(SEARCH("CDA",L36)),"CDA",IF(ISNUMBER(SEARCH("Fondo",L36)),"Fondo",0)))) -> Bonos | AD36: Otros | AE36: =IFERROR((MONTH(J36)),0) -> 5 | AF36: =IFERROR((YEAR(J36)),0) -> 2023
A37: Vencido | Cobrado | B37: Vencido | Cobrado | C37: BANCO BASA S.A. | D37: Intereses | E37: Vencido | Cobrado | F37: Grupo Cartes | G37: ASU CAPITAL CBSA | H37: PYBAM02F3500 | I37: 44704 | J37: 45159 | K37: AA-py Estable | L37: Bonos | M37: 0.06 | N37: =IF(AND(M37>#REF!,Cartera!O37="Guaraníes"),"Rendimiento significativo",IF(AND(M37>#REF!,Cartera!O37="Dólares americanos"),"Rendimiento significativo","Rendimiento no significativo")) -> #REF! | O37: Dólares americanos | P37: 373.9726 | Q37: =IF(O37="Guaraníes",P37,P37*#REF!) -> #REF! | R37: =IF(O37="Guaraníes",P37/#REF!,P37) -> 373.9726 | S37: Acreditado | V37: 14.958904 | AA37: 25 | AC37: =IF(ISNUMBER(SEARCH("Acciones",L37)),"Acciones",IF(ISNUMBER(SEARCH("Bono",L37)),"Bonos",IF(ISNUMBER(SEARCH("CDA",L37)),"CDA",IF(ISNUMBER(SEARCH("Fondo",L37)),"Fondo",0)))) -> Bonos | AD37: Otros | AE37: =IFERROR((MONTH(J37)),0) -> 8 | AF37: =IFERROR((YEAR(J37)),0) -> 2023
A38: Vencido | Cobrado | B38: Vencido | Cobrado | C38: BANCO BASA S.A. | D38: Intereses | E38: Vencido | Cobrado | F38: Grupo Cartes | G38: ASU CAPITAL CBSA | H38: PYBAM02F3500 | I38: 44704 | J38: 45250 | K38: AA-py Estable | L38: Bonos | M38: 0.06 | N38: =IF(AND(M38>#REF!,Cartera!O38="Guaraníes"),"Rendimiento significativo",IF(AND(M38>#REF!,Cartera!O38="Dólares americanos"),"Rendimiento significativo","Rendimiento no significativo")) -> #REF! | O38: Dólares americanos | P38: 373.9726 | Q38: =IF(O38="Guaraníes",P38,P38*#REF!) -> #REF! | R38: =IF(O38="Guaraníes",P38/#REF!,P38) -> 373.9726 | S38: Acreditado | V38: 14.958904 | AA38: 25 | AC38: =IF(ISNUMBER(SEARCH("Acciones",L38)),"Acciones",IF(ISNUMBER(SEARCH("Bono",L38)),"Bonos",IF(ISNUMBER(SEARCH("CDA",L38)),"CDA",IF(ISNUMBER(SEARCH("Fondo",L38)),"Fondo",0)))) -> Bonos | AD38: Otros | AE38: =IFERROR((MONTH(J38)),0) -> 11 | AF38: =IFERROR((YEAR(J38)),0) -> 2023
A39: Vencido | Cobrado | B39: Vencido | Cobrado | C39: BANCO BASA S.A. | D39: Intereses | E39: Vencido | Cobrado | F39: Grupo Cartes | G39: ASU CAPITAL CBSA | H39: PYBAM02F3500 | I39: 44704 | J39: 45341 | K39: AA-py Estable | L39: Bonos | M39: 0.06 | N39: =IF(AND(M39>#REF!,Cartera!O39="Guaraníes"),"Rendimiento significativo",IF(AND(M39>#REF!,Cartera!O39="Dólares americanos"),"Rendimiento significativo","Rendimiento no significativo")) -> #REF! | O39: Dólares americanos | P39: 373.9726 | Q39: =IF(O39="Guaraníes",P39,P39*#REF!) -> #REF! | R39: =IF(O39="Guaraníes",P39/#REF!,P39) -> 373.9726 | S39: Acreditado | V39: 14.958904 | AA39: 25 | AC39: =IF(ISNUMBER(SEARCH("Acciones",L39)),"Acciones",IF(ISNUMBER(SEARCH("Bono",L39)),"Bonos",IF(ISNUMBER(SEARCH("CDA",L39)),"CDA",IF(ISNUMBER(SEARCH("Fondo",L39)),"Fondo",0)))) -> Bonos | AD39: Otros | AE39: =IFERROR((MONTH(J39)),0) -> 2 | AF39: =IFERROR((YEAR(J39)),0) -> 2024
A40: Vencido | Cobrado | B40: Vencido | Cobrado | C40: BANCO BASA S.A. | D40: Intereses | E40: Vencido | Cobrado | F40: Grupo Cartes | G40: ASU CAPITAL CBSA | H40: PYBAM02F3500 | I40: 44704 | J40: 45432 | K40: AA-py Estable | L40: Bonos | M40: 0.06 | N40: =IF(AND(M40>#REF!,Cartera!O40="Guaraníes"),"Rendimiento significativo",IF(AND(M40>#REF!,Cartera!O40="Dólares americanos"),"Rendimiento significativo","Rendimiento no significativo")) -> #REF! | O40: Dólares americanos | P40: 373.9726 | Q40: =IF(O40="Guaraníes",P40,P40*#REF!) -> #REF! | R40: =IF(O40="Guaraníes",P40/#REF!,P40) -> 373.9726 | S40: Acreditado | V40: 14.958904 | AA40: 25 | AC40: =IF(ISNUMBER(SEARCH("Acciones",L40)),"Acciones",IF(ISNUMBER(SEARCH("Bono",L40)),"Bonos",IF(ISNUMBER(SEARCH("CDA",L40)),"CDA",IF(ISNUMBER(SEARCH("Fondo",L40)),"Fondo",0)))) -> Bonos | AD40: Otros | AE40: =IFERROR((MONTH(J40)),0) -> 5 | AF40: =IFERROR((YEAR(J40)),0) -> 2024
A41: Vencido | Cobrado | B41: Vencido | Cobrado | C41: TU FINANCIERA SAECA | D41: Intereses | E41: Vencido | Cobrado | F41: No aplica a grupos | H41: AA9801 | I41: 45314 | J41: 45405 | K41: A-py Estable | L41: CDA | M41: 0.098 | N41: =IF(AND(M41>#REF!,Cartera!O3527="Guaraníes"),"Rendimiento significativo",IF(AND(M41>#REF!,Cartera!O3527="Dólares americanos"),"Rendimiento significativo","Rendimiento no significativo")) -> #REF! | O41: Guaraníes | P41: 2579548 | Q41: =IF(O41="Guaraníes",P41,P41*#REF!) -> 2579548 | R41: =IF(O41="Guaraníes",P41/#REF!,P41) -> #REF! | S41: Acreditado | AC41: =IF(ISNUMBER(SEARCH("Acciones",L41)),"Acciones",IF(ISNUMBER(SEARCH("Bono",L41)),"Bonos",IF(ISNUMBER(SEARCH("CDA",L41)),"CDA",IF(ISNUMBER(SEARCH("Fondo",L41)),"Fondo",0)))) -> CDA | AD41: Otros | AE41: =IFERROR((MONTH(J41)),0) -> 4 | AF41: =IFERROR((YEAR(J41)),0) -> 2024
A42: Vencido | Cobrado | B42: Vencido | Cobrado | C42: RIEDER & CÍA. S.A.C.I. | D42: Intereses | E42: Vencido | Cobrado | F42: No aplica a grupos | G42: PUENTE CBSA | H42: PYRIE11F8577 | J42: 45301 | K42: pyBBB- Estable | L42: Bonos | M42: 0.09 | N42: =IF(AND(M42>#REF!,Cartera!O1819="Guaraníes"),"Rendimiento significativo",IF(AND(M42>#REF!,Cartera!O1819="Dólares americanos"),"Rendimiento significativo","Rendimiento no significativo")) -> #REF! | O42: Dólares americanos | P42: 235.78767 | Q42: =IF(O42="Guaraníes",P42,P42*#REF!) -> #REF! | R42: =IF(O42="Guaraníes",P42/#REF!,P42) -> 235.78767 | S42: Acreditado | T42: 3253 | W42: / | X42: 0 | Y42: 0 | Z42: 15.719178 | AA42: 15 | AB42: 235.78767 | AC42: =IF(ISNUMBER(SEARCH("Acciones",L42)),"Acciones",IF(ISNUMBER(SEARCH("Bono",L42)),"Bonos",IF(ISNUMBER(SEARCH("CDA",L42)),"CDA",IF(ISNUMBER(SEARCH("Fondo",L42)),"Fondo",0)))) -> Bonos | AD42: Otros | AE42: =IFERROR((MONTH(J42)),0) -> 1 | AF42: =IFERROR((YEAR(J42)),0) -> 2024
A43: 12315 | B43: Intereses Financieros a Cobrar LP - USD | C43: FIC DE FINANZAS | D43: Intereses | E43: Activo | F43: No aplica a grupos | I43: 45497 | J43: 45677 | L43: CDA | M43: 0.058 | O43: Dólares americanos | P43: 286.03 | Q43: =IF(O43="Guaraníes",P43,P43*#REF!) -> #REF! | R43: =IF(O43="Guaraníes",P43/#REF!,P43) -> 286.03 | S43: Pendiente | AC43: =IF(ISNUMBER(SEARCH("Acciones",L43)),"Acciones",IF(ISNUMBER(SEARCH("Bono",L43)),"Bonos",IF(ISNUMBER(SEARCH("CDA",L43)),"CDA",IF(ISNUMBER(SEARCH("Fondo",L43)),"Fondo",0)))) -> CDA | AD43: Otros | AE43: =IFERROR((MONTH(J43)),0) -> 1 | AF43: =IFERROR((YEAR(J43)),0) -> 2025
A44: 12316 | B44: Intereses Financieros a Cobrar LP - PYG | C44: FIC DE FINANZAS | D44: Intereses | E44: Activo | F44: No aplica a grupos | I44: 45497 | J44: 45677 | L44: CDA | M44: 0.074 | O44: Guaraníes | P44: 3193151 | Q44: =IF(O44="Guaraníes",P44,P44*#REF!) -> 3193151 | R44: =IF(O44="Guaraníes",P44/#REF!,P44) -> #REF! | S44: Pendiente | AC44: =IF(ISNUMBER(SEARCH("Acciones",L44)),"Acciones",IF(ISNUMBER(SEARCH("Bono",L44)),"Bonos",IF(ISNUMBER(SEARCH("CDA",L44)),"CDA",IF(ISNUMBER(SEARCH("Fondo",L44)),"Fondo",0)))) -> CDA | AD44: Otros | AE44: =IFERROR((MONTH(J44)),0) -> 1 | AF44: =IFERROR((YEAR(J44)),0) -> 2025
A45: 12315 | B45: Intereses Financieros a Cobrar LP - USD | C45: UENO HOLDING S.A.E.C.A. | D45: Intereses | E45: Activo | F45: No aplica a grupos | G45: FAIS CBSA | H45: PYPTP01F0861 | J45: 45679 | K45: A+py Estable | L45: Bonos | M45: 0.085 | N45: =IF(AND(M45>#REF!,Cartera!O1210="Guaraníes"),"Rendimiento significativo",IF(AND(M45>#REF!,Cartera!O1210="Dólares americanos"),"Rendimiento significativo","Rendimiento no significativo")) -> #REF! | O45: Dólares americanos | P45: 423.83562 | Q45: =IF(O45="Guaraníes",P45,P45*#REF!) -> #REF! | R45: =IF(O45="Guaraníes",P45/#REF!,P45) -> 423.83562 | S45: Pendiente | T45: 2475 | W45: / | X45: 0 | Y45: 0 | Z45: 21.191781 | AA45: 20 | AB45: 423.83562 | AC45: =IF(ISNUMBER(SEARCH("Acciones",L45)),"Acciones",IF(ISNUMBER(SEARCH("Bono",L45)),"Bonos",IF(ISNUMBER(SEARCH("CDA",L45)),"CDA",IF(ISNUMBER(SEARCH("Fondo",L45)),"Fondo",0)))) -> Bonos | AD45: Otros | AE45: =IFERROR((MONTH(J45)),0) -> 1 | AF45: =IFERROR((YEAR(J45)),0) -> 2025
A46: 12316 | B46: Intereses Financieros a Cobrar LP - PYG | C46: VISION BANCO S.A.E.C.A. | D46: Intereses | E46: Activo | F46: No aplica a grupos | G46: CADIEM CBSA | H46: PYVIS03F4624 | J46: 45680 | K46: Apy Estable | L46: Bonos Subordinados | M46: 0.125 | N46: =IF(AND(M46>#REF!,Cartera!O902="Guaraníes"),"Rendimiento significativo",IF(AND(M46>#REF!,Cartera!O902="Dólares americanos"),"Rendimiento significativo","Rendimiento no significativo")) -> #REF! | O46: Guaraníes | P46: 897534.25 | Q46: =IF(O46="Guaraníes",P46,P46*#REF!) -> 897534.25 | R46: =IF(O46="Guaraníes",P46/#REF!,P46) -> #REF! | S46: Pendiente | T46: 25 | W46: / | X46: 0 | Y46: 0 | Z46: 29917.808 | AA46: 30 | AB46: 897534.25 | AC46: =IF(ISNUMBER(SEARCH("Acciones",L46)),"Acciones",IF(ISNUMBER(SEARCH("Bono",L46)),"Bonos",IF(ISNUMBER(SEARCH("CDA",L46)),"CDA",IF(ISNUMBER(SEARCH("Fondo",L46)),"Fondo",0)))) -> Bonos | AD46: Otros | AE46: =IFERROR((MONTH(J46)),0) -> 1 | AF46: =IFERROR((YEAR(J46)),0) -> 2025
A47: 12316 | B47: Intereses Financieros a Cobrar LP - PYG | C47: TU FINANCIERA SAECA | D47: Intereses | E47: Activo | F47: No aplica a grupos | H47: AA9801 | I47: 45314 | J47: 45680 | K47: A-py Estable | L47: CDA | M47: 0.098 | N47: =IF(AND(M47>#REF!,Cartera!O3530="Guaraníes"),"Rendimiento significativo",IF(AND(M47>#REF!,Cartera!O3530="Dólares americanos"),"Rendimiento significativo","Rendimiento no significativo")) -> #REF! | O47: Guaraníes | P47: 2579548 | Q47: =IF(O47="Guaraníes",P47,P47*#REF!) -> 2579548 | R47: =IF(O47="Guaraníes",P47/#REF!,P47) -> #REF! | S47: Pendiente | AC47: =IF(ISNUMBER(SEARCH("Acciones",L47)),"Acciones",IF(ISNUMBER(SEARCH("Bono",L47)),"Bonos",IF(ISNUMBER(SEARCH("CDA",L47)),"CDA",IF(ISNUMBER(SEARCH("Fondo",L47)),"Fondo",0)))) -> CDA | AD47: Otros | AE47: =IFERROR((MONTH(J47)),0) -> 1 | AF47: =IFERROR((YEAR(J47)),0) -> 2025
A48: 12315 | B48: Intereses Financieros a Cobrar LP - USD | C48: CEMENTOS CONCEPCIÓN SOCIEDAD ANÓNIMA EMISORA | D48: Intereses | E48: Activo | F48: Grupo Cartes | G48: ASU CAPITAL CBSA | H48: PYCEC01F3409 | I48: 44680 | J48: 45681 | K48: pyAA- Estable | L48: Bonos | M48: 0.06 | N48: =IF(AND(M48>#REF!,Cartera!O14="Guaraníes"),"Rendimiento significativo",IF(AND(M48>#REF!,Cartera!O14="Dólares americanos"),"Rendimiento significativo","Rendimiento no significativo")) -> #REF! | O48: Dólares americanos | P48: 747.9452 | Q48: =IF(O48="Guaraníes",P48,P48*#REF!) -> #REF! | R48: =IF(O48="Guaraníes",P48/#REF!,P48) -> 747.9452 | S48: Pendiente | T48: 17035 | V48: 14.96 | AA48: 50 | AC48: =IF(ISNUMBER(SEARCH("Acciones",L48)),"Acciones",IF(ISNUMBER(SEARCH("Bono",L48)),"Bonos",IF(ISNUMBER(SEARCH("CDA",L48)),"CDA",IF(ISNUMBER(SEARCH("Fondo",L48)),"Fondo",0)))) -> Bonos | AD48: Otros | AE48: =IFERROR((MONTH(J48)),0) -> 1 | AF48: =IFERROR((YEAR(J48)),0) -> 2025
A49: 12315 | B49: Intereses Financieros a Cobrar LP - USD | C49: ZETA BANCO S.A.E.C.A. | D49: Intereses | E49: Activo | F49: No aplica a grupos | H49: AA2917 | I49: 45321 | J49: 45681 | K49: Apy Fuerte (+) | L49: CDA | M49: 0.055 | N49: =IF(AND(M49>#REF!,Cartera!O3535="Guaraníes"),"Rendimiento significativo",IF(AND(M49>#REF!,Cartera!O3535="Dólares americanos"),"Rendimiento significativo","Rendimiento no significativo")) -> #REF! | O49: Dólares americanos | P49: 530.41 | Q49: =IF(O49="Guaraníes",P49,P49*#REF!) -> #REF! | R49: =IF(O49="Guaraníes",P49/#REF!,P49) -> 530.41 | S49: Pendiente | AC49: =IF(ISNUMBER(SEARCH("Acciones",L49)),"Acciones",IF(ISNUMBER(SEARCH("Bono",L49)),"Bonos",IF(ISNUMBER(SEARCH("CDA",L49)),"CDA",IF(ISNUMBER(SEARCH("Fondo",L49)),"Fondo",0)))) -> CDA | AD49: Otros | AE49: =IFERROR((MONTH(J49)),0) -> 1 | AF49: =IFERROR((YEAR(J49)),0) -> 2025
A50: 12316 | B50: Intereses Financieros a Cobrar LP - PYG | C50: TU FINANCIERA SAECA | D50: Intereses | E50: Activo | F50: No aplica a grupos | H50: AC 1212 | I50: 45497 | J50: 45681 | L50: CDA | M50: 0.0835 | O50: Guaraníes | P50: 3151267 | Q50: =IF(O50="Guaraníes",P50,P50*#REF!) -> 3151267 | R50: =IF(O50="Guaraníes",P50/#REF!,P50) -> #REF! | S50: pendiente | AC50: =IF(ISNUMBER(SEARCH("Acciones",L50)),"Acciones",IF(ISNUMBER(SEARCH("Bono",L50)),"Bonos",IF(ISNUMBER(SEARCH("CDA",L50)),"CDA",IF(ISNUMBER(SEARCH("Fondo",L50)),"Fondo",0)))) -> CDA | AD50: Otros | AE50: =IFERROR((MONTH(J50)),0) -> 1 | AF50: =IFERROR((YEAR(J50)),0) -> 2025
A51: 12315 | B51: Intereses Financieros a Cobrar LP - USD | C51: TU FINANCIERA SAECA | D51: Intereses | E51: Activo | F51: No aplica a grupos | H51: AB0511 | I51: 45497 | J51: 45681 | L51: CDA | M51: 0.042 | O51: Dólares americanos | P51: 211 | Q51: =IF(O51="Guaraníes",P51,P51*#REF!) -> #REF! | R51: =IF(O51="Guaraníes",P51/#REF!,P51) -> 211 | S51: pendiente | AC51: =IF(ISNUMBER(SEARCH("Acciones",L51)),"Acciones",IF(ISNUMBER(SEARCH("Bono",L51)),"Bonos",IF(ISNUMBER(SEARCH("CDA",L51)),"CDA",IF(ISNUMBER(SEARCH("Fondo",L51)),"Fondo",0)))) -> CDA | AD51: Otros | AE51: =IFERROR((MONTH(J51)),0) -> 1 | AF51: =IFERROR((YEAR(J51)),0) -> 2025
A52: 12302 | B52: Inversiones en Bonos LP - USD | C52: BANCO BASA S.A. | D52: Capital | E52: Activo | F52: Grupo Cartes | G52: ASU CAPITAL CBSA | H52: PYBAM02F3500 | I52: 44704 | J52: 46524 | K52: AA-py Estable | L52: Bonos Financieros | M52: 0.06 | N52: =IF(AND(M52>#REF!,Cartera!O52="Guaraníes"),"Rendimiento significativo",IF(AND(M52>#REF!,Cartera!O52="Dólares americanos"),"Rendimiento significativo","Rendimiento no significativo")) -> #REF! | O52: Dólares americanos | P52: 25000 | Q52: =IF(O52="Guaraníes",P52,P52*#REF!) -> #REF! | R52: =IF(O52="Guaraníes",P52/#REF!,P52) -> 25000 | S52: Pendiente | V52: 14.958904 | AA52: 25 | AC52: =IF(ISNUMBER(SEARCH("Acciones",L52)),"Acciones",IF(ISNUMBER(SEARCH("Bono",L52)),"Bonos",IF(ISNUMBER(SEARCH("CDA",L52)),"CDA",IF(ISNUMBER(SEARCH("Fondo",L52)),"Fondo",0)))) -> Bonos | AD52: Otros | AE52: =IFERROR((MONTH(J52)),0) -> 5 | AF52: =IFERROR((YEAR(J52)),0) -> 2027
A53: Vencido | Cobrado | B53: Vencido | Cobrado | C53: BANCO CONTINENTAL S.A.E.C.A. | D53: Intereses | E53: Vencido | Cobrado | F53: Grupo Continental | G53: AVALON CBSA | H53: PYCON08F4900 | J53: 42375 | K53: AAApy Estable | L53: Bonos | M53: 0.13 | N53: =IF(AND(M53>#REF!,Cartera!O53="Guaraníes"),"Rendimiento significativo",IF(AND(M53>#REF!,Cartera!O53="Dólares americanos"),"Rendimiento significativo","Rendimiento no significativo")) -> #REF! | O53: Guaraníes | P53: 3276712.3 | Q53: =IF(O53="Guaraníes",P53,P53*#REF!) -> 3276712.3 | R53: =IF(O53="Guaraníes",P53/#REF!,P53) -> #REF! | S53: Acreditado | T53: 8 | W53: / | X53: 0 | Y53: 0 | Z53: 65534.247 | AA53: 50 | AB53: 3276712.3 | AC53: =IF(ISNUMBER(SEARCH("Acciones",L53)),"Acciones",IF(ISNUMBER(SEARCH("Bono",L53)),"Bonos",IF(ISNUMBER(SEARCH("CDA",L53)),"CDA",IF(ISNUMBER(SEARCH("Fondo",L53)),"Fondo",0)))) -> Bonos | AD53: Otros | AE53: =IFERROR((MONTH(J53)),0) -> 1 | AF53: =IFERROR((YEAR(J53)),0) -> 2016
A54: Vencido | Cobrado | B54: Vencido | Cobrado | C54: BANCO BILBAO VIZCAYA ARGENTARIA PARAGUAY S.A. | D54: Intereses | E54: Vencido | Cobrado | F54: No aplica a grupos | G54: AVALON CBSA | H54: PYBBV01F3798 | J54: 42506 | K54: A+py Fuerte | L54: Bonos | M54: 0.0675 | N54: =IF(AND(M54>#REF!,Cartera!O54="Guaraníes"),"Rendimiento significativo",IF(AND(M54>#REF!,Cartera!O54="Dólares americanos"),"Rendimiento significativo","Rendimiento no significativo")) -> #REF! | O54: Dólares americanos | P54: 1346.3014 | Q54: =IF(O54="Guaraníes",P54,P54*#REF!) -> #REF! | R54: =IF(O54="Guaraníes",P54/#REF!,P54) -> 1346.3014 | S54: Acreditado | T54: 8 | W54: / | X54: 0 | Y54: 0 | Z54: 33.657534 | AA54: 40 | AB54: 1346.3014 | AC54: =IF(ISNUMBER(SEARCH("Acciones",L54)),"Acciones",IF(ISNUMBER(SEARCH("Bono",L54)),"Bonos",IF(ISNUMBER(SEARCH("CDA",L54)),"CDA",IF(ISNUMBER(SEARCH("Fondo",L54)),"Fondo",0)))) -> Bonos | AD54: Otros | AE54: =IFERROR((MONTH(J54)),0) -> 5 | AF54: =IFERROR((YEAR(J54)),0) -> 2016
A55: Vencido | Cobrado | B55: Vencido | Cobrado | C55: BANCO CONTINENTAL S.A.E.C.A. | D55: Intereses | E55: Vencido | Cobrado | F55: Grupo Continental | G55: AVALON CBSA | H55: PYCON06F4720 | J55: 42543 | K55: AAApy Estable | L55: Bonos Subordinados | M55: 0.145 | N55: =IF(AND(M55>#REF!,Cartera!O55="Guaraníes"),"Rendimiento significativo",IF(AND(M55>#REF!,Cartera!O55="Dólares americanos"),"Rendimiento significativo","Rendimiento no significativo")) -> #REF! | O55: Guaraníes | P55: 7269863 | Q55: =IF(O55="Guaraníes",P55,P55*#REF!) -> 7269863 | R55: =IF(O55="Guaraníes",P55/#REF!,P55) -> #REF! | S55: Acreditado | T55: 8 | W55: / | X55: 0 | Y55: 0 | Z55: 72698.63 | AA55: 100 | AB55: 7269863 | AC55: =IF(ISNUMBER(SEARCH("Acciones",L55)),"Acciones",IF(ISNUMBER(SEARCH("Bono",L55)),"Bonos",IF(ISNUMBER(SEARCH("CDA",L55)),"CDA",IF(ISNUMBER(SEARCH("Fondo",L55)),"Fondo",0)))) -> Bonos | AD55: Otros | AE55: =IFERROR((MONTH(J55)),0) -> 6 | AF55: =IFERROR((YEAR(J55)),0) -> 2016
A56: Vencido | Cobrado | B56: Vencido | Cobrado | C56: BANCO CONTINENTAL S.A.E.C.A. | D56: Intereses | E56: Vencido | Cobrado | F56: Grupo Continental | G56: AVALON CBSA | H56: PYCON08F4900 | J56: 42557 | K56: AAApy Estable | L56: Bonos | M56: 0.13 | N56: =IF(AND(M56>#REF!,Cartera!O56="Guaraníes"),"Rendimiento significativo",IF(AND(M56>#REF!,Cartera!O56="Dólares americanos"),"Rendimiento significativo","Rendimiento no significativo")) -> #REF! | O56: Guaraníes | P56: 3241095.9 | Q56: =IF(O56="Guaraníes",P56,P56*#REF!) -> 3241095.9 | R56: =IF(O56="Guaraníes",P56/#REF!,P56) -> #REF! | S56: Acreditado | T56: 8 | W56: / | X56: 0 | Y56: 0 | Z56: 64821.918 | AA56: 50 | AB56: 3241095.9 | AC56: =IF(ISNUMBER(SEARCH("Acciones",L56)),"Acciones",IF(ISNUMBER(SEARCH("Bono",L56)),"Bonos",IF(ISNUMBER(SEARCH("CDA",L56)),"CDA",IF(ISNUMBER(SEARCH("Fondo",L56)),"Fondo",0)))) -> Bonos | AD56: Otros | AE56: =IFERROR((MONTH(J56)),0) -> 7 | AF56: =IFERROR((YEAR(J56)),0) -> 2016
A57: Vencido | Cobrado | B57: Vencido | Cobrado | C57: BANCO BILBAO VIZCAYA ARGENTARIA PARAGUAY S.A. | D57: Intereses | E57: Vencido | Cobrado | F57: No aplica a grupos | G57: AVALON CBSA | H57: PYBBV01F3798 | J57: 42688 | K57: A+py Fuerte | L57: Bonos | M57: 0.0675 | N57: =IF(AND(M57>#REF!,Cartera!O57="Guaraníes"),"Rendimiento significativo",IF(AND(M57>#REF!,Cartera!O57="Dólares americanos"),"Rendimiento significativo","Rendimiento no significativo")) -> #REF! | O57: Dólares americanos | P57: 1346.3014 | Q57: =IF(O57="Guaraníes",P57,P57*#REF!) -> #REF! | R57: =IF(O57="Guaraníes",P57/#REF!,P57) -> 1346.3014 | S57: Acreditado | T57: 8 | W57: / | X57: 0 | Y57: 0 | Z57: 33.657534 | AA57: 40 | AB57: 1346.3014 | AC57: =IF(ISNUMBER(SEARCH("Acciones",L57)),"Acciones",IF(ISNUMBER(SEARCH("Bono",L57)),"Bonos",IF(ISNUMBER(SEARCH("CDA",L57)),"CDA",IF(ISNUMBER(SEARCH("Fondo",L57)),"Fondo",0)))) -> Bonos | AD57: Otros | AE57: =IFERROR((MONTH(J57)),0) -> 11 | AF57: =IFERROR((YEAR(J57)),0) -> 2016
A58: Vencido | Cobrado | B58: Vencido | Cobrado | C58: BANCO CONTINENTAL S.A.E.C.A. | D58: Intereses | E58: Vencido | Cobrado | F58: Grupo Continental | G58: AVALON CBSA | H58: PYCON06F4720 | J58: 42726 | K58: AAApy Estable | L58: Bonos Subordinados | M58: 0.145 | N58: =IF(AND(M58>#REF!,Cartera!O58="Guaraníes"),"Rendimiento significativo",IF(AND(M58>#REF!,Cartera!O58="Dólares americanos"),"Rendimiento significativo","Rendimiento no significativo")) -> #REF! | O58: Guaraníes | P58: 7269863 | Q58: =IF(O58="Guaraníes",P58,P58*#REF!) -> 7269863 | R58: =IF(O58="Guaraníes",P58/#REF!,P58) -> #REF! | S58: Acreditado | T58: 8 | W58: / | X58: 0 | Y58: 0 | Z58: 72698.63 | AA58: 100 | AB58: 7269863 | AC58: =IF(ISNUMBER(SEARCH("Acciones",L58)),"Acciones",IF(ISNUMBER(SEARCH("Bono",L58)),"Bonos",IF(ISNUMBER(SEARCH("CDA",L58)),"CDA",IF(ISNUMBER(SEARCH("Fondo",L58)),"Fondo",0)))) -> Bonos | AD58: Otros | AE58: =IFERROR((MONTH(J58)),0) -> 12 | AF58: =IFERROR((YEAR(J58)),0) -> 2016
A59: Vencido | Cobrado | B59: Vencido | Cobrado | C59: BANCO CONTINENTAL S.A.E.C.A. | D59: Intereses | E59: Vencido | Cobrado | F59: Grupo Continental | G59: AVALON CBSA | H59: PYCON08F4900 | J59: 42741 | K59: AAApy Estable | L59: Bonos | M59: 0.13 | N59: =IF(AND(M59>#REF!,Cartera!O59="Guaraníes"),"Rendimiento significativo",IF(AND(M59>#REF!,Cartera!O59="Dólares americanos"),"Rendimiento significativo","Rendimiento no significativo")) -> #REF! | O59: Guaraníes | P59: 3276712.3 | Q59: =IF(O59="Guaraníes",P59,P59*#REF!) -> 3276712.3 | R59: =IF(O59="Guaraníes",P59/#REF!,P59) -> #REF! | S59: Acreditado | T59: 8 | W59: / | X59: 0 | Y59: 0 | Z59: 65534.247 | AA59: 50 | AB59: 3276712.3 | AC59: =IF(ISNUMBER(SEARCH("Acciones",L59)),"Acciones",IF(ISNUMBER(SEARCH("Bono",L59)),"Bonos",IF(ISNUMBER(SEARCH("CDA",L59)),"CDA",IF(ISNUMBER(SEARCH("Fondo",L59)),"Fondo",0)))) -> Bonos | AD59: Otros | AE59: =IFERROR((MONTH(J59)),0) -> 1 | AF59: =IFERROR((YEAR(J59)),0) -> 2017
A60: Vencido | Cobrado | B60: Vencido | Cobrado | C60: BANCO CONTINENTAL S.A.E.C.A. | D60: Intereses | E60: Vencido | Cobrado | F60: Grupo Continental | G60: AVALON CBSA | H60: PYCON01F6605 | J60: 42755 | K60: AAApy Estable | L60: Bonos | M60: 0.12 | N60: =IF(AND(M60>#REF!,Cartera!O60="Guaraníes"),"Rendimiento significativo",IF(AND(M60>#REF!,Cartera!O60="Dólares americanos"),"Rendimiento significativo","Rendimiento no significativo")) -> #REF! | O60: Guaraníes | P60: 2991780.8 | Q60: =IF(O60="Guaraníes",P60,P60*#REF!) -> 2991780.8 | R60: =IF(O60="Guaraníes",P60/#REF!,P60) -> #REF! | S60: Acreditado | T60: 8 | W60: / | X60: 0 | Y60: 0 | Z60: 59835.616 | AA60: 50 | AB60: 2991780.8 | AC60: =IF(ISNUMBER(SEARCH("Acciones",L60)),"Acciones",IF(ISNUMBER(SEARCH("Bono",L60)),"Bonos",IF(ISNUMBER(SEARCH("CDA",L60)),"CDA",IF(ISNUMBER(SEARCH("Fondo",L60)),"Fondo",0)))) -> Bonos | AD60: Otros | AE60: =IFERROR((MONTH(J60)),0) -> 1 | AF60: =IFERROR((YEAR(J60)),0) -> 2017
A61: Vencido | Cobrado | B61: Vencido | Cobrado | C61: BANCO BILBAO VIZCAYA ARGENTARIA PARAGUAY S.A. | D61: Intereses | E61: Vencido | Cobrado | F61: No aplica a grupos | G61: AVALON CBSA | H61: PYBBV01F3798 | J61: 42871 | K61: A+py Fuerte | L61: Bonos | M61: 0.0675 | N61: =IF(AND(M61>#REF!,Cartera!O61="Guaraníes"),"Rendimiento significativo",IF(AND(M61>#REF!,Cartera!O61="Dólares americanos"),"Rendimiento significativo","Rendimiento no significativo")) -> #REF! | O61: Dólares americanos | P61: 1353.6986 | Q61: =IF(O61="Guaraníes",P61,P61*#REF!) -> #REF! | R61: =IF(O61="Guaraníes",P61/#REF!,P61) -> 1353.6986 | S61: Acreditado | T61: 8 | W61: / | X61: 0 | Y61: 0 | Z61: 33.842466 | AA61: 40 | AB61: 1353.6986 | AC61: =IF(ISNUMBER(SEARCH("Acciones",L61)),"Acciones",IF(ISNUMBER(SEARCH("Bono",L61)),"Bonos",IF(ISNUMBER(SEARCH("CDA",L61)),"CDA",IF(ISNUMBER(SEARCH("Fondo",L61)),"Fondo",0)))) -> Bonos | AD61: Otros | AE61: =IFERROR((MONTH(J61)),0) -> 5 | AF61: =IFERROR((YEAR(J61)),0) -> 2017
A62: Vencido | Cobrado | B62: Vencido | Cobrado | C62: BANCO CONTINENTAL S.A.E.C.A. | D62: Intereses | E62: Vencido | Cobrado | F62: Grupo Continental | G62: AVALON CBSA | H62: PYCON06F4720 | J62: 42908 | K62: AAApy Estable | L62: Bonos Subordinados | M62: 0.145 | N62: =IF(AND(M62>#REF!,Cartera!O62="Guaraníes"),"Rendimiento significativo",IF(AND(M62>#REF!,Cartera!O62="Dólares americanos"),"Rendimiento significativo","Rendimiento no significativo")) -> #REF! | O62: Guaraníes | P62: 7230137 | Q62: =IF(O62="Guaraníes",P62,P62*#REF!) -> 7230137 | R62: =IF(O62="Guaraníes",P62/#REF!,P62) -> #REF! | S62: Acreditado | T62: 8 | W62: / | X62: 0 | Y62: 0 | Z62: 72301.37 | AA62: 100 | AB62: 7230137 | AC62: =IF(ISNUMBER(SEARCH("Acciones",L62)),"Acciones",IF(ISNUMBER(SEARCH("Bono",L62)),"Bonos",IF(ISNUMBER(SEARCH("CDA",L62)),"CDA",IF(ISNUMBER(SEARCH("Fondo",L62)),"Fondo",0)))) -> Bonos | AD62: Otros | AE62: =IFERROR((MONTH(J62)),0) -> 6 | AF62: =IFERROR((YEAR(J62)),0) -> 2017
A63: Vencido | Cobrado | B63: Vencido | Cobrado | C63: BANCO CONTINENTAL S.A.E.C.A. | D63: Intereses | E63: Vencido | Cobrado | F63: Grupo Continental | G63: AVALON CBSA | H63: PYCON08F4900 | J63: 42923 | K63: AAApy Estable | L63: Bonos | M63: 0.13 | N63: =IF(AND(M63>#REF!,Cartera!O63="Guaraníes"),"Rendimiento significativo",IF(AND(M63>#REF!,Cartera!O63="Dólares americanos"),"Rendimiento significativo","Rendimiento no significativo")) -> #REF! | O63: Guaraníes | P63: 3241095.9 | Q63: =IF(O63="Guaraníes",P63,P63*#REF!) -> 3241095.9 | R63: =IF(O63="Guaraníes",P63/#REF!,P63) -> #REF! | S63: Acreditado | T63: 8 | W63: / | X63: 0 | Y63: 0 | Z63: 64821.918 | AA63: 50 | AB63: 3241095.9 | AC63: =IF(ISNUMBER(SEARCH("Acciones",L63)),"Acciones",IF(ISNUMBER(SEARCH("Bono",L63)),"Bonos",IF(ISNUMBER(SEARCH("CDA",L63)),"CDA",IF(ISNUMBER(SEARCH("Fondo",L63)),"Fondo",0)))) -> Bonos | AD63: Otros | AE63: =IFERROR((MONTH(J63)),0) -> 7 | AF63: =IFERROR((YEAR(J63)),0) -> 2017
A64: Vencido | Cobrado | B64: Vencido | Cobrado | C64: BANCO CONTINENTAL S.A.E.C.A. | D64: Intereses | E64: Vencido | Cobrado | F64: Grupo Continental | G64: AVALON CBSA | H64: PYCON01F6605 | J64: 42937 | K64: AAApy Estable | L64: Bonos | M64: 0.12 | N64: =IF(AND(M64>#REF!,Cartera!O64="Guaraníes"),"Rendimiento significativo",IF(AND(M64>#REF!,Cartera!O64="Dólares americanos"),"Rendimiento significativo","Rendimiento no significativo")) -> #REF! | O64: Guaraníes | P64: 2991780.8 | Q64: =IF(O64="Guaraníes",P64,P64*#REF!) -> 2991780.8 | R64: =IF(O64="Guaraníes",P64/#REF!,P64) -> #REF! | S64: Acreditado | T64: 8 | W64: / | X64: 0 | Y64: 0 | Z64: 59835.616 | AA64: 50 | AB64: 2991780.8 | AC64: =IF(ISNUMBER(SEARCH("Acciones",L64)),"Acciones",IF(ISNUMBER(SEARCH("Bono",L64)),"Bonos",IF(ISNUMBER(SEARCH("CDA",L64)),"CDA",IF(ISNUMBER(SEARCH("Fondo",L64)),"Fondo",0)))) -> Bonos | AD64: Otros | AE64: =IFERROR((MONTH(J64)),0) -> 7 | AF64: =IFERROR((YEAR(J64)),0) -> 2017
A65: 12303 | B65: Acciones en Otras Empresas LP - PYG | C65: BANCO CONTINENTAL S.A.E.C.A. | D65: Capital | E65: Activo | F65: Grupo Continental | H65: Acciones Preferidas "C" | I65: 42940 | J65: No aplica | Acciones | K65: AAApy Estable | L65: Acciones | M65: 0.01 | N65: =IF(AND(M65>#REF!,Cartera!O65="Guaraníes"),"Rendimiento significativo",IF(AND(M65>#REF!,Cartera!O65="Dólares americanos"),"Rendimiento significativo","Rendimiento no significativo")) -> #REF! | O65: Guaraníes | P65: 114200000 | Q65: =IF(O65="Guaraníes",P65,P65*#REF!) -> 114200000 | R65: =IF(O65="Guaraníes",P65/#REF!,P65) -> #REF! | S65: Pendiente | AC65: =IF(ISNUMBER(SEARCH("Acciones",L65)),"Acciones",IF(ISNUMBER(SEARCH("Bono",L65)),"Bonos",IF(ISNUMBER(SEARCH("CDA",L65)),"CDA",IF(ISNUMBER(SEARCH("Fondo",L65)),"Fondo",0)))) -> Acciones | AD65: Otros | AE65: =IFERROR((MONTH(J65)),0) -> 0 | AF65: =IFERROR((YEAR(J65)),0) -> 0
A66: Vencido | Cobrado | B66: Vencido | Cobrado | C66: ZETA BANCO S.A.E.C.A. | D66: Intereses | E66: Vencido | Cobrado | F66: No aplica a grupos | G66: AVALON CBSA | H66: PYFIN02F6708 | J66: 42955 | K66: Apy Fuerte (+) | L66: Bonos | M66: 0.07 | N66: =IF(AND(M66>#REF!,Cartera!O66="Guaraníes"),"Rendimiento significativo",IF(AND(M66>#REF!,Cartera!O66="Dólares americanos"),"Rendimiento significativo","Rendimiento no significativo")) -> #REF! | O66: Dólares americanos | P66: 56.09589 | Q66: =IF(O66="Guaraníes",P66,P66*#REF!) -> #REF! | R66: =IF(O66="Guaraníes",P66/#REF!,P66) -> 56.09589 | S66: Acreditado | T66: 8 | W66: / | X66: 0 | Y66: 0 | Z66: 18.69863 | AA66: 3 | AB66: 56.09589 | AC66: =IF(ISNUMBER(SEARCH("Acciones",L66)),"Acciones",IF(ISNUMBER(SEARCH("Bono",L66)),"Bonos",IF(ISNUMBER(SEARCH("CDA",L66)),"CDA",IF(ISNUMBER(SEARCH("Fondo",L66)),"Fondo",0)))) -> Bonos | AD66: Otros | AE66: =IFERROR((MONTH(J66)),0) -> 8 | AF66: =IFERROR((YEAR(J66)),0) -> 2017
A67: Vencido | Cobrado | B67: Vencido | Cobrado | C67: ZETA BANCO S.A.E.C.A. | D67: Intereses | E67: Vencido | Cobrado | F67: No aplica a grupos | G67: AVALON CBSA | H67: PYFIN02F6708 | J67: 43046 | K67: Apy Fuerte (+) | L67: Bonos | M67: 0.07 | N67: =IF(AND(M67>#REF!,Cartera!O67="Guaraníes"),"Rendimiento significativo",IF(AND(M67>#REF!,Cartera!O67="Dólares americanos"),"Rendimiento significativo","Rendimiento no significativo")) -> #REF! | O67: Dólares americanos | P67: 56.09589 | Q67: =IF(O67="Guaraníes",P67,P67*#REF!) -> #REF! | R67: =IF(O67="Guaraníes",P67/#REF!,P67) -> 56.09589 | S67: Acreditado | T67: 8 | W67: / | X67: 0 | Y67: 0 | Z67: 18.69863 | AA67: 3 | AB67: 56.09589 | AC67: =IF(ISNUMBER(SEARCH("Acciones",L67)),"Acciones",IF(ISNUMBER(SEARCH("Bono",L67)),"Bonos",IF(ISNUMBER(SEARCH("CDA",L67)),"CDA",IF(ISNUMBER(SEARCH("Fondo",L67)),"Fondo",0)))) -> Bonos | AD67: Otros | AE67: =IFERROR((MONTH(J67)),0) -> 11 | AF67: =IFERROR((YEAR(J67)),0) -> 2017
A68: Vencido | Cobrado | B68: Vencido | Cobrado | C68: BANCO BILBAO VIZCAYA ARGENTARIA PARAGUAY S.A. | D68: Intereses | E68: Vencido | Cobrado | F68: No aplica a grupos | G68: AVALON CBSA | H68: PYBBV01F3798 | J68: 43052 | K68: A+py Fuerte | L68: Bonos | M68: 0.0675 | N68: =IF(AND(M68>#REF!,Cartera!O68="Guaraníes"),"Rendimiento significativo",IF(AND(M68>#REF!,Cartera!O68="Dólares americanos"),"Rendimiento significativo","Rendimiento no significativo")) -> #REF! | O68: Dólares americanos | P68: 1338.9041 | Q68: =IF(O68="Guaraníes",P68,P68*#REF!) -> #REF! | R68: =IF(O68="Guaraníes",P68/#REF!,P68) -> 1338.9041 | S68: Acreditado | T68: 8 | W68: / | X68: 0 | Y68: 0 | Z68: 33.472603 | AA68: 40 | AB68: 1338.9041 | AC68: =IF(ISNUMBER(SEARCH("Acciones",L68)),"Acciones",IF(ISNUMBER(SEARCH("Bono",L68)),"Bonos",IF(ISNUMBER(SEARCH("CDA",L68)),"CDA",IF(ISNUMBER(SEARCH("Fondo",L68)),"Fondo",0)))) -> Bonos | AD68: Otros | AE68: =IFERROR((MONTH(J68)),0) -> 11 | AF68: =IFERROR((YEAR(J68)),0) -> 2017
A69: Vencido | Cobrado | B69: Vencido | Cobrado | C69: BANCO CONTINENTAL S.A.E.C.A. | D69: Intereses | E69: Vencido | Cobrado | F69: Grupo Continental | G69: AVALON CBSA | H69: PYCON06F4720 | J69: 43091 | K69: AAApy Estable | L69: Bonos Subordinados | M69: 0.145 | N69: =IF(AND(M69>#REF!,Cartera!O69="Guaraníes"),"Rendimiento significativo",IF(AND(M69>#REF!,Cartera!O69="Dólares americanos"),"Rendimiento significativo","Rendimiento no significativo")) -> #REF! | O69: Guaraníes | P69: 7269863 | Q69: =IF(O69="Guaraníes",P69,P69*#REF!) -> 7269863 | R69: =IF(O69="Guaraníes",P69/#REF!,P69) -> #REF! | S69: Acreditado | T69: 8 | W69: / | X69: 0 | Y69: 0 | Z69: 72698.63 | AA69: 100 | AB69: 7269863 | AC69: =IF(ISNUMBER(SEARCH("Acciones",L69)),"Acciones",IF(ISNUMBER(SEARCH("Bono",L69)),"Bonos",IF(ISNUMBER(SEARCH("CDA",L69)),"CDA",IF(ISNUMBER(SEARCH("Fondo",L69)),"Fondo",0)))) -> Bonos | AD69: Otros | AE69: =IFERROR((MONTH(J69)),0) -> 12 | AF69: =IFERROR((YEAR(J69)),0) -> 2017
A70: Vencido | Cobrado | B70: Vencido | Cobrado | C70: BANCO CONTINENTAL S.A.E.C.A. | D70: Intereses | E70: Vencido | Cobrado | F70: Grupo Continental | G70: AVALON CBSA | H70: PYCON08F4900 | J70: 43105 | K70: AAApy Estable | L70: Bonos | M70: 0.13 | N70: =IF(AND(M70>#REF!,Cartera!O70="Guaraníes"),"Rendimiento significativo",IF(AND(M70>#REF!,Cartera!O70="Dólares americanos"),"Rendimiento significativo","Rendimiento no significativo")) -> #REF! | O70: Guaraníes | P70: 3241095.9 | Q70: =IF(O70="Guaraníes",P70,P70*#REF!) -> 3241095.9 | R70: =IF(O70="Guaraníes",P70/#REF!,P70) -> #REF! | S70: Acreditado | T70: 8 | W70: / | X70: 0 | Y70: 0 | Z70: 64821.918 | AA70: 50 | AB70: 3241095.9 | AC70: =IF(ISNUMBER(SEARCH("Acciones",L70)),"Acciones",IF(ISNUMBER(SEARCH("Bono",L70)),"Bonos",IF(ISNUMBER(SEARCH("CDA",L70)),"CDA",IF(ISNUMBER(SEARCH("Fondo",L70)),"Fondo",0)))) -> Bonos | AD70: Otros | AE70: =IFERROR((MONTH(J70)),0) -> 1 | AF70: =IFERROR((YEAR(J70)),0) -> 2018
A71: Vencido | Cobrado | B71: Vencido | Cobrado | C71: BANCO CONTINENTAL S.A.E.C.A. | D71: Intereses | E71: Vencido | Cobrado | F71: Grupo Continental | G71: AVALON CBSA | H71: PYCON01F6605 | J71: 43119 | K71: AAApy Estable | L71: Bonos | M71: 0.12 | N71: =IF(AND(M71>#REF!,Cartera!O71="Guaraníes"),"Rendimiento significativo",IF(AND(M71>#REF!,Cartera!O71="Dólares americanos"),"Rendimiento significativo","Rendimiento no significativo")) -> #REF! | O71: Guaraníes | P71: 2991780.8 | Q71: =IF(O71="Guaraníes",P71,P71*#REF!) -> 2991780.8 | R71: =IF(O71="Guaraníes",P71/#REF!,P71) -> #REF! | S71: Acreditado | T71: 8 | W71: / | X71: 0 | Y71: 0 | Z71: 59835.616 | AA71: 50 | AB71: 2991780.8 | AC71: =IF(ISNUMBER(SEARCH("Acciones",L71)),"Acciones",IF(ISNUMBER(SEARCH("Bono",L71)),"Bonos",IF(ISNUMBER(SEARCH("CDA",L71)),"CDA",IF(ISNUMBER(SEARCH("Fondo",L71)),"Fondo",0)))) -> Bonos | AD71: Otros | AE71: =IFERROR((MONTH(J71)),0) -> 1 | AF71: =IFERROR((YEAR(J71)),0) -> 2018
A72: Vencido | Cobrado | B72: Vencido | Cobrado | C72: ZETA BANCO S.A.E.C.A. | D72: Intereses | E72: Vencido | Cobrado | F72: No aplica a grupos | G72: AVALON CBSA | H72: PYFIN02F6708 | J72: 43137 | K72: Apy Fuerte (+) | L72: Bonos | M72: 0.07 | N72: =IF(AND(M72>#REF!,Cartera!O72="Guaraníes"),"Rendimiento significativo",IF(AND(M72>#REF!,Cartera!O72="Dólares americanos"),"Rendimiento significativo","Rendimiento no significativo")) -> #REF! | O72: Dólares americanos | P72: 56.09589 | Q72: =IF(O72="Guaraníes",P72,P72*#REF!) -> #REF! | R72: =IF(O72="Guaraníes",P72/#REF!,P72) -> 56.09589 | S72: Acreditado | T72: 8 | W72: / | X72: 0 | Y72: 0 | Z72: 18.69863 | AA72: 3 | AB72: 56.09589 | AC72: =IF(ISNUMBER(SEARCH("Acciones",L72)),"Acciones",IF(ISNUMBER(SEARCH("Bono",L72)),"Bonos",IF(ISNUMBER(SEARCH("CDA",L72)),"CDA",IF(ISNUMBER(SEARCH("Fondo",L72)),"Fondo",0)))) -> Bonos | AD72: Otros | AE72: =IFERROR((MONTH(J72)),0) -> 2 | AF72: =IFERROR((YEAR(J72)),0) -> 2018
A73: 12303 | B73: Acciones en Otras Empresas LP - PYG | C73: BANCO CONTINENTAL S.A.E.C.A. | D73: Capital | E73: Activo | F73: Grupo Continental | H73: Acciones Preferidas "C" | I73: 43222 | J73: No aplica | Acciones | K73: AAApy Estable | L73: Acciones | M73: 0.01 | N73: =IF(AND(M73>#REF!,Cartera!O73="Guaraníes"),"Rendimiento significativo",IF(AND(M73>#REF!,Cartera!O73="Dólares americanos"),"Rendimiento significativo","Rendimiento no significativo")) -> #REF! | O73: Guaraníes | P73: 10100000 | Q73: =IF(O73="Guaraníes",P73,P73*#REF!) -> 10100000 | R73: =IF(O73="Guaraníes",P73/#REF!,P73) -> #REF! | S73: Pendiente | AC73: =IF(ISNUMBER(SEARCH("Acciones",L73)),"Acciones",IF(ISNUMBER(SEARCH("Bono",L73)),"Bonos",IF(ISNUMBER(SEARCH("CDA",L73)),"CDA",IF(ISNUMBER(SEARCH("Fondo",L73)),"Fondo",0)))) -> Acciones | AD73: Otros | AE73: =IFERROR((MONTH(J73)),0) -> 0 | AF73: =IFERROR((YEAR(J73)),0) -> 0
A74: Vencido | Cobrado | B74: Vencido | Cobrado | C74: ZETA BANCO S.A.E.C.A. | D74: Intereses | E74: Vencido | Cobrado | F74: No aplica a grupos | G74: AVALON CBSA | H74: PYFIN02F6708 | J74: 43228 | K74: Apy Fuerte (+) | L74: Bonos | M74: 0.07 | N74: =IF(AND(M74>#REF!,Cartera!O74="Guaraníes"),"Rendimiento significativo",IF(AND(M74>#REF!,Cartera!O74="Dólares americanos"),"Rendimiento significativo","Rendimiento no significativo")) -> #REF! | O74: Dólares americanos | P74: 56.09589 | Q74: =IF(O74="Guaraníes",P74,P74*#REF!) -> #REF! | R74: =IF(O74="Guaraníes",P74/#REF!,P74) -> 56.09589 | S74: Acreditado | T74: 8 | W74: / | X74: 0 | Y74: 0 | Z74: 18.69863 | AA74: 3 | AB74: 56.09589 | AC74: =IF(ISNUMBER(SEARCH("Acciones",L74)),"Acciones",IF(ISNUMBER(SEARCH("Bono",L74)),"Bonos",IF(ISNUMBER(SEARCH("CDA",L74)),"CDA",IF(ISNUMBER(SEARCH("Fondo",L74)),"Fondo",0)))) -> Bonos | AD74: Otros | AE74: =IFERROR((MONTH(J74)),0) -> 5 | AF74: =IFERROR((YEAR(J74)),0) -> 2018
A75: Vencido | Cobrado | B75: Vencido | Cobrado | C75: BANCO BILBAO VIZCAYA ARGENTARIA PARAGUAY S.A. | D75: Intereses | E75: Vencido | Cobrado | F75: No aplica a grupos | G75: AVALON CBSA | H75: PYBBV01F3798 | J75: 43231 | K75: A+py Fuerte | L75: Bonos | M75: 0.0675 | N75: =IF(AND(M75>#REF!,Cartera!O75="Guaraníes"),"Rendimiento significativo",IF(AND(M75>#REF!,Cartera!O75="Dólares americanos"),"Rendimiento significativo","Rendimiento no significativo")) -> #REF! | O75: Dólares americanos | P75: 1324.1096 | Q75: =IF(O75="Guaraníes",P75,P75*#REF!) -> #REF! | R75: =IF(O75="Guaraníes",P75/#REF!,P75) -> 1324.1096 | S75: Acreditado | T75: 8 | W75: / | X75: 0 | Y75: 0 | Z75: 33.10274 | AA75: 40 | AB75: 1324.1096 | AC75: =IF(ISNUMBER(SEARCH("Acciones",L75)),"Acciones",IF(ISNUMBER(SEARCH("Bono",L75)),"Bonos",IF(ISNUMBER(SEARCH("CDA",L75)),"CDA",IF(ISNUMBER(SEARCH("Fondo",L75)),"Fondo",0)))) -> Bonos | AD75: Otros | AE75: =IFERROR((MONTH(J75)),0) -> 5 | AF75: =IFERROR((YEAR(J75)),0) -> 2018
A76: Vencido | Cobrado | B76: Vencido | Cobrado | C76: BANCO CONTINENTAL S.A.E.C.A. | D76: Intereses | E76: Vencido | Cobrado | F76: Grupo Continental | G76: AVALON CBSA | H76: PYCON06F4720 | J76: 43273 | K76: AAApy Estable | L76: Bonos Subordinados | M76: 0.145 | N76: =IF(AND(M76>#REF!,Cartera!O76="Guaraníes"),"Rendimiento significativo",IF(AND(M76>#REF!,Cartera!O76="Dólares americanos"),"Rendimiento significativo","Rendimiento no significativo")) -> #REF! | O76: Guaraníes | P76: 7230137 | Q76: =IF(O76="Guaraníes",P76,P76*#REF!) -> 7230137 | R76: =IF(O76="Guaraníes",P76/#REF!,P76) -> #REF! | S76: Acreditado | T76: 8 | W76: / | X76: 0 | Y76: 0 | Z76: 72301.37 | AA76: 100 | AB76: 7230137 | AC76: =IF(ISNUMBER(SEARCH("Acciones",L76)),"Acciones",IF(ISNUMBER(SEARCH("Bono",L76)),"Bonos",IF(ISNUMBER(SEARCH("CDA",L76)),"CDA",IF(ISNUMBER(SEARCH("Fondo",L76)),"Fondo",0)))) -> Bonos | AD76: Otros | AE76: =IFERROR((MONTH(J76)),0) -> 6 | AF76: =IFERROR((YEAR(J76)),0) -> 2018
A77: Vencido | Cobrado | B77: Vencido | Cobrado | C77: BANCO CONTINENTAL S.A.E.C.A. | D77: Intereses | E77: Vencido | Cobrado | F77: Grupo Continental | G77: AVALON CBSA | H77: PYCON08F4900 | J77: 43287 | K77: AAApy Estable | L77: Bonos | M77: 0.13 | N77: =IF(AND(M77>#REF!,Cartera!O77="Guaraníes"),"Rendimiento significativo",IF(AND(M77>#REF!,Cartera!O77="Dólares americanos"),"Rendimiento significativo","Rendimiento no significativo")) -> #REF! | O77: Guaraníes | P77: 3241095.9 | Q77: =IF(O77="Guaraníes",P77,P77*#REF!) -> 3241095.9 | R77: =IF(O77="Guaraníes",P77/#REF!,P77) -> #REF! | S77: Acreditado | T77: 8 | W77: / | X77: 0 | Y77: 0 | Z77: 64821.918 | AA77: 50 | AB77: 3241095.9 | AC77: =IF(ISNUMBER(SEARCH("Acciones",L77)),"Acciones",IF(ISNUMBER(SEARCH("Bono",L77)),"Bonos",IF(ISNUMBER(SEARCH("CDA",L77)),"CDA",IF(ISNUMBER(SEARCH("Fondo",L77)),"Fondo",0)))) -> Bonos | AD77: Otros | AE77: =IFERROR((MONTH(J77)),0) -> 7 | AF77: =IFERROR((YEAR(J77)),0) -> 2018
A78: Vencido | Cobrado | B78: Vencido | Cobrado | C78: BANCO CONTINENTAL S.A.E.C.A. | D78: Intereses | E78: Vencido | Cobrado | F78: Grupo Continental | G78: AVALON CBSA | H78: PYCON01F6605 | J78: 43301 | K78: AAApy Estable | L78: Bonos | M78: 0.12 | N78: =IF(AND(M78>#REF!,Cartera!O78="Guaraníes"),"Rendimiento significativo",IF(AND(M78>#REF!,Cartera!O78="Dólares americanos"),"Rendimiento significativo","Rendimiento no significativo")) -> #REF! | O78: Guaraníes | P78: 2991780.8 | Q78: =IF(O78="Guaraníes",P78,P78*#REF!) -> 2991780.8 | R78: =IF(O78="Guaraníes",P78/#REF!,P78) -> #REF! | S78: Acreditado | T78: 8 | W78: / | X78: 0 | Y78: 0 | Z78: 59835.616 | AA78: 50 | AB78: 2991780.8 | AC78: =IF(ISNUMBER(SEARCH("Acciones",L78)),"Acciones",IF(ISNUMBER(SEARCH("Bono",L78)),"Bonos",IF(ISNUMBER(SEARCH("CDA",L78)),"CDA",IF(ISNUMBER(SEARCH("Fondo",L78)),"Fondo",0)))) -> Bonos | AD78: Otros | AE78: =IFERROR((MONTH(J78)),0) -> 7 | AF78: =IFERROR((YEAR(J78)),0) -> 2018
A79: Vencido | Cobrado | B79: Vencido | Cobrado | C79: ZETA BANCO S.A.E.C.A. | D79: Intereses | E79: Vencido | Cobrado | F79: No aplica a grupos | G79: AVALON CBSA | H79: PYFIN02F6708 | J79: 43319 | K79: Apy Fuerte (+) | L79: Bonos | M79: 0.07 | N79: =IF(AND(M79>#REF!,Cartera!O79="Guaraníes"),"Rendimiento significativo",IF(AND(M79>#REF!,Cartera!O79="Dólares americanos"),"Rendimiento significativo","Rendimiento no significativo")) -> #REF! | O79: Dólares americanos | P79: 56.09589 | Q79: =IF(O79="Guaraníes",P79,P79*#REF!) -> #REF! | R79: =IF(O79="Guaraníes",P79/#REF!,P79) -> 56.09589 | S79: Acreditado | T79: 8 | W79: / | X79: 0 | Y79: 0 | Z79: 18.69863 | AA79: 3 | AB79: 56.09589 | AC79: =IF(ISNUMBER(SEARCH("Acciones",L79)),"Acciones",IF(ISNUMBER(SEARCH("Bono",L79)),"Bonos",IF(ISNUMBER(SEARCH("CDA",L79)),"CDA",IF(ISNUMBER(SEARCH("Fondo",L79)),"Fondo",0)))) -> Bonos | AD79: Otros | AE79: =IFERROR((MONTH(J79)),0) -> 8 | AF79: =IFERROR((YEAR(J79)),0) -> 2018
A80: Vencido | Cobrado | B80: Vencido | Cobrado | C80: ZETA BANCO S.A.E.C.A. | D80: Intereses | E80: Vencido | Cobrado | F80: No aplica a grupos | G80: AVALON CBSA | H80: PYFIN02F6708 | J80: 43410 | K80: Apy Fuerte (+) | L80: Bonos | M80: 0.07 | N80: =IF(AND(M80>#REF!,Cartera!O80="Guaraníes"),"Rendimiento significativo",IF(AND(M80>#REF!,Cartera!O80="Dólares americanos"),"Rendimiento significativo","Rendimiento no significativo")) -> #REF! | O80: Dólares americanos | P80: 56.09589 | Q80: =IF(O80="Guaraníes",P80,P80*#REF!) -> #REF! | R80: =IF(O80="Guaraníes",P80/#REF!,P80) -> 56.09589 | S80: Acreditado | T80: 8 | W80: / | X80: 0 | Y80: 0 | Z80: 18.69863 | AA80: 3 | AB80: 56.09589 | AC80: =IF(ISNUMBER(SEARCH("Acciones",L80)),"Acciones",IF(ISNUMBER(SEARCH("Bono",L80)),"Bonos",IF(ISNUMBER(SEARCH("CDA",L80)),"CDA",IF(ISNUMBER(SEARCH("Fondo",L80)),"Fondo",0)))) -> Bonos | AD80: Otros | AE80: =IFERROR((MONTH(J80)),0) -> 11 | AF80: =IFERROR((YEAR(J80)),0) -> 2018
A81: Vencido | Cobrado | B81: Vencido | Cobrado | C81: BANCO BILBAO VIZCAYA ARGENTARIA PARAGUAY S.A. | D81: Intereses | E81: Vencido | Cobrado | F81: No aplica a grupos | G81: AVALON CBSA | H81: PYBBV01F3798 | J81: 43413 | K81: A+py Fuerte | L81: Bonos | M81: 0.0675 | N81: =IF(AND(M81>#REF!,Cartera!O81="Guaraníes"),"Rendimiento significativo",IF(AND(M81>#REF!,Cartera!O81="Dólares americanos"),"Rendimiento significativo","Rendimiento no significativo")) -> #REF! | O81: Dólares americanos | P81: 1346.3014 | Q81: =IF(O81="Guaraníes",P81,P81*#REF!) -> #REF! | R81: =IF(O81="Guaraníes",P81/#REF!,P81) -> 1346.3014 | S81: Acreditado | T81: 8 | W81: / | X81: 0 | Y81: 0 | Z81: 33.657534 | AA81: 40 | AB81: 1346.3014 | AC81: =IF(ISNUMBER(SEARCH("Acciones",L81)),"Acciones",IF(ISNUMBER(SEARCH("Bono",L81)),"Bonos",IF(ISNUMBER(SEARCH("CDA",L81)),"CDA",IF(ISNUMBER(SEARCH("Fondo",L81)),"Fondo",0)))) -> Bonos | AD81: Otros | AE81: =IFERROR((MONTH(J81)),0) -> 11 | AF81: =IFERROR((YEAR(J81)),0) -> 2018
A82: Vencido | Cobrado | B82: Vencido | Cobrado | C82: BANCO CONTINENTAL S.A.E.C.A. | D82: Intereses | E82: Vencido | Cobrado | F82: Grupo Continental | G82: AVALON CBSA | H82: PYCON06F4720 | J82: 43455 | K82: AAApy Estable | L82: Bonos Subordinados | M82: 0.145 | N82: =IF(AND(M82>#REF!,Cartera!O82="Guaraníes"),"Rendimiento significativo",IF(AND(M82>#REF!,Cartera!O82="Dólares americanos"),"Rendimiento significativo","Rendimiento no significativo")) -> #REF! | O82: Guaraníes | P82: 7230137 | Q82: =IF(O82="Guaraníes",P82,P82*#REF!) -> 7230137 | R82: =IF(O82="Guaraníes",P82/#REF!,P82) -> #REF! | S82: Acreditado | T82: 8 | W82: / | X82: 0 | Y82: 0 | Z82: 72301.37 | AA82: 100 | AB82: 7230137 | AC82: =IF(ISNUMBER(SEARCH("Acciones",L82)),"Acciones",IF(ISNUMBER(SEARCH("Bono",L82)),"Bonos",IF(ISNUMBER(SEARCH("CDA",L82)),"CDA",IF(ISNUMBER(SEARCH("Fondo",L82)),"Fondo",0)))) -> Bonos | AD82: Otros | AE82: =IFERROR((MONTH(J82)),0) -> 12 | AF82: =IFERROR((YEAR(J82)),0) -> 2018
A83: Vencido | Cobrado | B83: Vencido | Cobrado | C83: BANCO CONTINENTAL S.A.E.C.A. | D83: Intereses | E83: Vencido | Cobrado | F83: Grupo Continental | G83: AVALON CBSA | H83: PYCON08F4900 | J83: 43469 | K83: AAApy Estable | L83: Bonos | M83: 0.13 | N83: =IF(AND(M83>#REF!,Cartera!O83="Guaraníes"),"Rendimiento significativo",IF(AND(M83>#REF!,Cartera!O83="Dólares americanos"),"Rendimiento significativo","Rendimiento no significativo")) -> #REF! | O83: Guaraníes | P83: 3241095.9 | Q83: =IF(O83="Guaraníes",P83,P83*#REF!) -> 3241095.9 | R83: =IF(O83="Guaraníes",P83/#REF!,P83) -> #REF! | S83: Acreditado | T83: 8 | W83: / | X83: 0 | Y83: 0 | Z83: 64821.918 | AA83: 50 | AB83: 3241095.9 | AC83: =IF(ISNUMBER(SEARCH("Acciones",L83)),"Acciones",IF(ISNUMBER(SEARCH("Bono",L83)),"Bonos",IF(ISNUMBER(SEARCH("CDA",L83)),"CDA",IF(ISNUMBER(SEARCH("Fondo",L83)),"Fondo",0)))) -> Bonos | AD83: Otros | AE83: =IFERROR((MONTH(J83)),0) -> 1 | AF83: =IFERROR((YEAR(J83)),0) -> 2019
A84: Vencido | Cobrado | B84: Vencido | Cobrado | C84: BANCO CONTINENTAL S.A.E.C.A. | D84: Intereses | E84: Vencido | Cobrado | F84: Grupo Continental | G84: AVALON CBSA | H84: PYCON01F6605 | J84: 43483 | K84: AAApy Estable | L84: Bonos | M84: 0.12 | N84: =IF(AND(M84>#REF!,Cartera!O84="Guaraníes"),"Rendimiento significativo",IF(AND(M84>#REF!,Cartera!O84="Dólares americanos"),"Rendimiento significativo","Rendimiento no significativo")) -> #REF! | O84: Guaraníes | P84: 2991780.8 | Q84: =IF(O84="Guaraníes",P84,P84*#REF!) -> 2991780.8 | R84: =IF(O84="Guaraníes",P84/#REF!,P84) -> #REF! | S84: Acreditado | T84: 8 | W84: / | X84: 0 | Y84: 0 | Z84: 59835.616 | AA84: 50 | AB84: 2991780.8 | AC84: =IF(ISNUMBER(SEARCH("Acciones",L84)),"Acciones",IF(ISNUMBER(SEARCH("Bono",L84)),"Bonos",IF(ISNUMBER(SEARCH("CDA",L84)),"CDA",IF(ISNUMBER(SEARCH("Fondo",L84)),"Fondo",0)))) -> Bonos | AD84: Otros | AE84: =IFERROR((MONTH(J84)),0) -> 1 | AF84: =IFERROR((YEAR(J84)),0) -> 2019
A85: Vencido | Cobrado | B85: Vencido | Cobrado | C85: ZETA BANCO S.A.E.C.A. | D85: Intereses | E85: Vencido | Cobrado | F85: No aplica a grupos | G85: AVALON CBSA | H85: PYFIN02F6708 | J85: 43501 | K85: Apy Fuerte (+) | L85: Bonos | M85: 0.07 | N85: =IF(AND(M85>#REF!,Cartera!O85="Guaraníes"),"Rendimiento significativo",IF(AND(M85>#REF!,Cartera!O85="Dólares americanos"),"Rendimiento significativo","Rendimiento no significativo")) -> #REF! | O85: Dólares americanos | P85: 56.09589 | Q85: =IF(O85="Guaraníes",P85,P85*#REF!) -> #REF! | R85: =IF(O85="Guaraníes",P85/#REF!,P85) -> 56.09589 | S85: Acreditado | T85: 8 | W85: / | X85: 0 | Y85: 0 | Z85: 18.69863 | AA85: 3 | AB85: 56.09589 | AC85: =IF(ISNUMBER(SEARCH("Acciones",L85)),"Acciones",IF(ISNUMBER(SEARCH("Bono",L85)),"Bonos",IF(ISNUMBER(SEARCH("CDA",L85)),"CDA",IF(ISNUMBER(SEARCH("Fondo",L85)),"Fondo",0)))) -> Bonos | AD85: Otros | AE85: =IFERROR((MONTH(J85)),0) -> 2 | AF85: =IFERROR((YEAR(J85)),0) -> 2019
A86: 12303 | B86: Acciones en Otras Empresas LP - PYG | C86: BANCO CONTINENTAL S.A.E.C.A. | D86: Capital | E86: Activo | F86: Grupo Continental | H86: Acciones Preferidas "C" | I86: 43587 | J86: No aplica | Acciones | K86: AAApy Estable | L86: Acciones | M86: 0.01 | N86: =IF(AND(M86>#REF!,Cartera!O86="Guaraníes"),"Rendimiento significativo",IF(AND(M86>#REF!,Cartera!O86="Dólares americanos"),"Rendimiento significativo","Rendimiento no significativo")) -> #REF! | O86: Guaraníes | P86: 7200000 | Q86: =IF(O86="Guaraníes",P86,P86*#REF!) -> 7200000 | R86: =IF(O86="Guaraníes",P86/#REF!,P86) -> #REF! | S86: Pendiente | AC86: =IF(ISNUMBER(SEARCH("Acciones",L86)),"Acciones",IF(ISNUMBER(SEARCH("Bono",L86)),"Bonos",IF(ISNUMBER(SEARCH("CDA",L86)),"CDA",IF(ISNUMBER(SEARCH("Fondo",L86)),"Fondo",0)))) -> Acciones | AD86: Otros | AE86: =IFERROR((MONTH(J86)),0) -> 0 | AF86: =IFERROR((YEAR(J86)),0) -> 0
A87: Vencido | Cobrado | B87: Vencido | Cobrado | C87: ZETA BANCO S.A.E.C.A. | D87: Intereses | E87: Vencido | Cobrado | F87: No aplica a grupos | G87: AVALON CBSA | H87: PYFIN02F6708 | J87: 43593 | K87: Apy Fuerte (+) | L87: Bonos | M87: 0.07 | N87: =IF(AND(M87>#REF!,Cartera!O87="Guaraníes"),"Rendimiento significativo",IF(AND(M87>#REF!,Cartera!O87="Dólares americanos"),"Rendimiento significativo","Rendimiento no significativo")) -> #REF! | O87: Dólares americanos | P87: 56.71233 | Q87: =IF(O87="Guaraníes",P87,P87*#REF!) -> #REF! | R87: =IF(O87="Guaraníes",P87/#REF!,P87) -> 56.71233 | S87: Acreditado | T87: 8 | W87: / | X87: 0 | Y87: 0 | Z87: 18.90411 | AA87: 3 | AB87: 56.71233 | AC87: =IF(ISNUMBER(SEARCH("Acciones",L87)),"Acciones",IF(ISNUMBER(SEARCH("Bono",L87)),"Bonos",IF(ISNUMBER(SEARCH("CDA",L87)),"CDA",IF(ISNUMBER(SEARCH("Fondo",L87)),"Fondo",0)))) -> Bonos | AD87: Otros | AE87: =IFERROR((MONTH(J87)),0) -> 5 | AF87: =IFERROR((YEAR(J87)),0) -> 2019
A88: Vencido | Cobrado | B88: Vencido | Cobrado | C88: BANCO BILBAO VIZCAYA ARGENTARIA PARAGUAY S.A. | D88: Intereses | E88: Vencido | Cobrado | F88: No aplica a grupos | G88: AVALON CBSA | H88: PYBBV01F3798 | J88: 43595 | K88: A+py Fuerte | L88: Bonos | M88: 0.0675 | N88: =IF(AND(M88>#REF!,Cartera!O88="Guaraníes"),"Rendimiento significativo",IF(AND(M88>#REF!,Cartera!O88="Dólares americanos"),"Rendimiento significativo","Rendimiento no significativo")) -> #REF! | O88: Dólares americanos | P88: 1346.3014 | Q88: =IF(O88="Guaraníes",P88,P88*#REF!) -> #REF! | R88: =IF(O88="Guaraníes",P88/#REF!,P88) -> 1346.3014 | S88: Acreditado | T88: 8 | W88: / | X88: 0 | Y88: 0 | Z88: 33.657534 | AA88: 40 | AB88: 1346.3014 | AC88: =IF(ISNUMBER(SEARCH("Acciones",L88)),"Acciones",IF(ISNUMBER(SEARCH("Bono",L88)),"Bonos",IF(ISNUMBER(SEARCH("CDA",L88)),"CDA",IF(ISNUMBER(SEARCH("Fondo",L88)),"Fondo",0)))) -> Bonos | AD88: Otros | AE88: =IFERROR((MONTH(J88)),0) -> 5 | AF88: =IFERROR((YEAR(J88)),0) -> 2019
A89: Vencido | Cobrado | B89: Vencido | Cobrado | C89: BANCO CONTINENTAL S.A.E.C.A. | D89: Intereses | E89: Vencido | Cobrado | F89: Grupo Continental | G89: AVALON CBSA | H89: PYCON06F4720 | J89: 43640 | K89: AAApy Estable | L89: Bonos Subordinados | M89: 0.145 | N89: =IF(AND(M89>#REF!,Cartera!O89="Guaraníes"),"Rendimiento significativo",IF(AND(M89>#REF!,Cartera!O89="Dólares americanos"),"Rendimiento significativo","Rendimiento no significativo")) -> #REF! | O89: Guaraníes | P89: 7349315.1 | Q89: =IF(O89="Guaraníes",P89,P89*#REF!) -> 7349315.1 | R89: =IF(O89="Guaraníes",P89/#REF!,P89) -> #REF! | S89: Acreditado | T89: 8 | W89: / | X89: 0 | Y89: 0 | Z89: 73493.151 | AA89: 100 | AB89: 7349315.1 | AC89: =IF(ISNUMBER(SEARCH("Acciones",L89)),"Acciones",IF(ISNUMBER(SEARCH("Bono",L89)),"Bonos",IF(ISNUMBER(SEARCH("CDA",L89)),"CDA",IF(ISNUMBER(SEARCH("Fondo",L89)),"Fondo",0)))) -> Bonos | AD89: Otros | AE89: =IFERROR((MONTH(J89)),0) -> 6 | AF89: =IFERROR((YEAR(J89)),0) -> 2019
A90: Vencido | Cobrado | B90: Vencido | Cobrado | C90: BANCO CONTINENTAL S.A.E.C.A. | D90: Intereses | E90: Vencido | Cobrado | F90: Grupo Continental | G90: AVALON CBSA | H90: PYCON08F4900 | J90: 43651 | K90: AAApy Estable | L90: Bonos | M90: 0.13 | N90: =IF(AND(M90>#REF!,Cartera!O90="Guaraníes"),"Rendimiento significativo",IF(AND(M90>#REF!,Cartera!O90="Dólares americanos"),"Rendimiento significativo","Rendimiento no significativo")) -> #REF! | O90: Guaraníes | P90: 3241095.9 | Q90: =IF(O90="Guaraníes",P90,P90*#REF!) -> 3241095.9 | R90: =IF(O90="Guaraníes",P90/#REF!,P90) -> #REF! | S90: Acreditado | T90: 8 | W90: / | X90: 0 | Y90: 0 | Z90: 64821.918 | AA90: 50 | AB90: 3241095.9 | AC90: =IF(ISNUMBER(SEARCH("Acciones",L90)),"Acciones",IF(ISNUMBER(SEARCH("Bono",L90)),"Bonos",IF(ISNUMBER(SEARCH("CDA",L90)),"CDA",IF(ISNUMBER(SEARCH("Fondo",L90)),"Fondo",0)))) -> Bonos | AD90: Otros | AE90: =IFERROR((MONTH(J90)),0) -> 7 | AF90: =IFERROR((YEAR(J90)),0) -> 2019
A91: Vencido | Cobrado | B91: Vencido | Cobrado | C91: BANCO CONTINENTAL S.A.E.C.A. | D91: Intereses | E91: Vencido | Cobrado | F91: Grupo Continental | G91: AVALON CBSA | H91: PYCON01F6605 | J91: 43665 | K91: AAApy Estable | L91: Bonos | M91: 0.12 | N91: =IF(AND(M91>#REF!,Cartera!O91="Guaraníes"),"Rendimiento significativo",IF(AND(M91>#REF!,Cartera!O91="Dólares americanos"),"Rendimiento significativo","Rendimiento no significativo")) -> #REF! | O91: Guaraníes | P91: 2991780.8 | Q91: =IF(O91="Guaraníes",P91,P91*#REF!) -> 2991780.8 | R91: =IF(O91="Guaraníes",P91/#REF!,P91) -> #REF! | S91: Acreditado | T91: 8 | W91: / | X91: 0 | Y91: 0 | Z91: 59835.616 | AA91: 50 | AB91: 2991780.8 | AC91: =IF(ISNUMBER(SEARCH("Acciones",L91)),"Acciones",IF(ISNUMBER(SEARCH("Bono",L91)),"Bonos",IF(ISNUMBER(SEARCH("CDA",L91)),"CDA",IF(ISNUMBER(SEARCH("Fondo",L91)),"Fondo",0)))) -> Bonos | AD91: Otros | AE91: =IFERROR((MONTH(J91)),0) -> 7 | AF91: =IFERROR((YEAR(J91)),0) -> 2019
A92: Vencido | Cobrado | B92: Vencido | Cobrado | C92: ZETA BANCO S.A.E.C.A. | D92: Intereses | E92: Vencido | Cobrado | F92: No aplica a grupos | G92: AVALON CBSA | H92: PYFIN02F6708 | J92: 43683 | K92: Apy Fuerte (+) | L92: Bonos | M92: 0.07 | N92: =IF(AND(M92>#REF!,Cartera!O92="Guaraníes"),"Rendimiento significativo",IF(AND(M92>#REF!,Cartera!O92="Dólares americanos"),"Rendimiento significativo","Rendimiento no significativo")) -> #REF! | O92: Dólares americanos | P92: 55.479453 | Q92: =IF(O92="Guaraníes",P92,P92*#REF!) -> #REF! | R92: =IF(O92="Guaraníes",P92/#REF!,P92) -> 55.479453 | S92: Acreditado | T92: 8 | W92: / | X92: 0 | Y92: 0 | Z92: 18.493151 | AA92: 3 | AB92: 55.479453 | AC92: =IF(ISNUMBER(SEARCH("Acciones",L92)),"Acciones",IF(ISNUMBER(SEARCH("Bono",L92)),"Bonos",IF(ISNUMBER(SEARCH("CDA",L92)),"CDA",IF(ISNUMBER(SEARCH("Fondo",L92)),"Fondo",0)))) -> Bonos | AD92: Otros | AE92: =IFERROR((MONTH(J92)),0) -> 8 | AF92: =IFERROR((YEAR(J92)),0) -> 2019
A93: Vencido | Cobrado | B93: Vencido | Cobrado | C93: ZETA BANCO S.A.E.C.A. | D93: Intereses | E93: Vencido | Cobrado | F93: No aplica a grupos | G93: AVALON CBSA | H93: PYFIN02F6708 | J93: 43774 | K93: Apy Fuerte (+) | L93: Bonos | M93: 0.07 | N93: =IF(AND(M93>#REF!,Cartera!O93="Guaraníes"),"Rendimiento significativo",IF(AND(M93>#REF!,Cartera!O93="Dólares americanos"),"Rendimiento significativo","Rendimiento no significativo")) -> #REF! | O93: Dólares americanos | P93: 56.09589 | Q93: =IF(O93="Guaraníes",P93,P93*#REF!) -> #REF! | R93: =IF(O93="Guaraníes",P93/#REF!,P93) -> 56.09589 | S93: Acreditado | T93: 8 | W93: / | X93: 0 | Y93: 0 | Z93: 18.69863 | AA93: 3 | AB93: 56.09589 | AC93: =IF(ISNUMBER(SEARCH("Acciones",L93)),"Acciones",IF(ISNUMBER(SEARCH("Bono",L93)),"Bonos",IF(ISNUMBER(SEARCH("CDA",L93)),"CDA",IF(ISNUMBER(SEARCH("Fondo",L93)),"Fondo",0)))) -> Bonos | AD93: Otros | AE93: =IFERROR((MONTH(J93)),0) -> 11 | AF93: =IFERROR((YEAR(J93)),0) -> 2019
A94: Vencido | Cobrado | B94: Vencido | Cobrado | C94: BANCO BILBAO VIZCAYA ARGENTARIA PARAGUAY S.A. | D94: Intereses | E94: Vencido | Cobrado | F94: No aplica a grupos | G94: AVALON CBSA | H94: PYBBV01F3798 | J94: 43777 | K94: A+py Fuerte | L94: Bonos | M94: 0.0675 | N94: =IF(AND(M94>#REF!,Cartera!O94="Guaraníes"),"Rendimiento significativo",IF(AND(M94>#REF!,Cartera!O94="Dólares americanos"),"Rendimiento significativo","Rendimiento no significativo")) -> #REF! | O94: Dólares americanos | P94: 1346.3014 | Q94: =IF(O94="Guaraníes",P94,P94*#REF!) -> #REF! | R94: =IF(O94="Guaraníes",P94/#REF!,P94) -> 1346.3014 | S94: Acreditado | T94: 8 | W94: / | X94: 0 | Y94: 0 | Z94: 33.657534 | AA94: 40 | AB94: 1346.3014 | AC94: =IF(ISNUMBER(SEARCH("Acciones",L94)),"Acciones",IF(ISNUMBER(SEARCH("Bono",L94)),"Bonos",IF(ISNUMBER(SEARCH("CDA",L94)),"CDA",IF(ISNUMBER(SEARCH("Fondo",L94)),"Fondo",0)))) -> Bonos | AD94: Otros | AE94: =IFERROR((MONTH(J94)),0) -> 11 | AF94: =IFERROR((YEAR(J94)),0) -> 2019
A95: Vencido | Cobrado | B95: Vencido | Cobrado | C95: BANCO CONTINENTAL S.A.E.C.A. | D95: Intereses | E95: Vencido | Cobrado | F95: Grupo Continental | G95: AVALON CBSA | H95: PYCON06F4720 | J95: 43822 | K95: AAApy Estable | L95: Bonos Subordinados | M95: 0.145 | N95: =IF(AND(M95>#REF!,Cartera!O95="Guaraníes"),"Rendimiento significativo",IF(AND(M95>#REF!,Cartera!O95="Dólares americanos"),"Rendimiento significativo","Rendimiento no significativo")) -> #REF! | O95: Guaraníes | P95: 7230137 | Q95: =IF(O95="Guaraníes",P95,P95*#REF!) -> 7230137 | R95: =IF(O95="Guaraníes",P95/#REF!,P95) -> #REF! | S95: Acreditado | T95: 8 | W95: / | X95: 0 | Y95: 0 | Z95: 72301.37 | AA95: 100 | AB95: 7230137 | AC95: =IF(ISNUMBER(SEARCH("Acciones",L95)),"Acciones",IF(ISNUMBER(SEARCH("Bono",L95)),"Bonos",IF(ISNUMBER(SEARCH("CDA",L95)),"CDA",IF(ISNUMBER(SEARCH("Fondo",L95)),"Fondo",0)))) -> Bonos | AD95: Otros | AE95: =IFERROR((MONTH(J95)),0) -> 12 | AF95: =IFERROR((YEAR(J95)),0) -> 2019
A96: Vencido | Cobrado | B96: Vencido | Cobrado | C96: BANCO CONTINENTAL S.A.E.C.A. | D96: Intereses | E96: Vencido | Cobrado | F96: Grupo Continental | G96: AVALON CBSA | H96: PYCON08F4900 | J96: 43833 | K96: AAApy Estable | L96: Bonos | M96: 0.13 | N96: =IF(AND(M96>#REF!,Cartera!O96="Guaraníes"),"Rendimiento significativo",IF(AND(M96>#REF!,Cartera!O96="Dólares americanos"),"Rendimiento significativo","Rendimiento no significativo")) -> #REF! | O96: Guaraníes | P96: 3241095.9 | Q96: =IF(O96="Guaraníes",P96,P96*#REF!) -> 3241095.9 | R96: =IF(O96="Guaraníes",P96/#REF!,P96) -> #REF! | S96: Acreditado | T96: 8 | W96: / | X96: 0 | Y96: 0 | Z96: 64821.918 | AA96: 50 | AB96: 3241095.9 | AC96: =IF(ISNUMBER(SEARCH("Acciones",L96)),"Acciones",IF(ISNUMBER(SEARCH("Bono",L96)),"Bonos",IF(ISNUMBER(SEARCH("CDA",L96)),"CDA",IF(ISNUMBER(SEARCH("Fondo",L96)),"Fondo",0)))) -> Bonos | AD96: Otros | AE96: =IFERROR((MONTH(J96)),0) -> 1 | AF96: =IFERROR((YEAR(J96)),0) -> 2020
A97: Vencido | Cobrado | B97: Vencido | Cobrado | C97: BANCO CONTINENTAL S.A.E.C.A. | D97: Intereses | E97: Vencido | Cobrado | F97: Grupo Continental | G97: AVALON CBSA | H97: PYCON01F6605 | J97: 43847 | K97: AAApy Estable | L97: Bonos | M97: 0.12 | N97: =IF(AND(M97>#REF!,Cartera!O97="Guaraníes"),"Rendimiento significativo",IF(AND(M97>#REF!,Cartera!O97="Dólares americanos"),"Rendimiento significativo","Rendimiento no significativo")) -> #REF! | O97: Guaraníes | P97: 2991780.8 | Q97: =IF(O97="Guaraníes",P97,P97*#REF!) -> 2991780.8 | R97: =IF(O97="Guaraníes",P97/#REF!,P97) -> #REF! | S97: Acreditado | T97: 8 | W97: / | X97: 0 | Y97: 0 | Z97: 59835.616 | AA97: 50 | AB97: 2991780.8 | AC97: =IF(ISNUMBER(SEARCH("Acciones",L97)),"Acciones",IF(ISNUMBER(SEARCH("Bono",L97)),"Bonos",IF(ISNUMBER(SEARCH("CDA",L97)),"CDA",IF(ISNUMBER(SEARCH("Fondo",L97)),"Fondo",0)))) -> Bonos | AD97: Otros | AE97: =IFERROR((MONTH(J97)),0) -> 1 | AF97: =IFERROR((YEAR(J97)),0) -> 2020
A98: Vencido | Cobrado | B98: Vencido | Cobrado | C98: ZETA BANCO S.A.E.C.A. | D98: Intereses | E98: Vencido | Cobrado | F98: No aplica a grupos | G98: AVALON CBSA | H98: PYFIN02F6708 | J98: 43865 | K98: Apy Fuerte (+) | L98: Bonos | M98: 0.07 | N98: =IF(AND(M98>#REF!,Cartera!O98="Guaraníes"),"Rendimiento significativo",IF(AND(M98>#REF!,Cartera!O98="Dólares americanos"),"Rendimiento significativo","Rendimiento no significativo")) -> #REF! | O98: Dólares americanos | P98: 56.09589 | Q98: =IF(O98="Guaraníes",P98,P98*#REF!) -> #REF! | R98: =IF(O98="Guaraníes",P98/#REF!,P98) -> 56.09589 | S98: Acreditado | T98: 8 | W98: / | X98: 0 | Y98: 0 | Z98: 18.69863 | AA98: 3 | AB98: 56.09589 | AC98: =IF(ISNUMBER(SEARCH("Acciones",L98)),"Acciones",IF(ISNUMBER(SEARCH("Bono",L98)),"Bonos",IF(ISNUMBER(SEARCH("CDA",L98)),"CDA",IF(ISNUMBER(SEARCH("Fondo",L98)),"Fondo",0)))) -> Bonos | AD98: Otros | AE98: =IFERROR((MONTH(J98)),0) -> 2 | AF98: =IFERROR((YEAR(J98)),0) -> 2020
A99: Vencido | Cobrado | B99: Vencido | Cobrado | C99: BANCO CONTINENTAL S.A.E.C.A. | D99: Intereses | E99: Vencido | Cobrado | F99: Grupo Continental | G99: PUENTE CBSA | H99: PYCON06F7996 | J99: 43950 | K99: AAApy Estable | L99: Bonos Subordinados | M99: 0.06 | N99: =IF(AND(M99>#REF!,Cartera!O99="Guaraníes"),"Rendimiento significativo",IF(AND(M99>#REF!,Cartera!O99="Dólares americanos"),"Rendimiento significativo","Rendimiento no significativo")) -> #REF! | O99: Dólares americanos | P99: 299.17808 | Q99: =IF(O99="Guaraníes",P99,P99*#REF!) -> #REF! | R99: =IF(O99="Guaraníes",P99/#REF!,P99) -> 299.17808 | S99: Acreditado | T99: 3253 | W99: / | X99: 0 | Y99: 0 | Z99: 29.917808 | AA99: 10 | AB99: 299.17808 | AC99: =IF(ISNUMBER(SEARCH("Acciones",L99)),"Acciones",IF(ISNUMBER(SEARCH("Bono",L99)),"Bonos",IF(ISNUMBER(SEARCH("CDA",L99)),"CDA",IF(ISNUMBER(SEARCH("Fondo",L99)),"Fondo",0)))) -> Bonos | AD99: Otros | AE99: =IFERROR((MONTH(J99)),0) -> 4 | AF99: =IFERROR((YEAR(J99)),0) -> 2020
A100: 12303 | B100: Acciones en Otras Empresas LP - PYG | C100: BANCO CONTINENTAL S.A.E.C.A. | D100: Capital | E100: Activo | F100: Grupo Continental | H100: Acciones Preferidas "C" | I100: 43955 | J100: No aplica | Acciones | K100: AAApy Estable | L100: Acciones | M100: 0.06 | N100: =IF(AND(M100>#REF!,Cartera!O100="Guaraníes"),"Rendimiento significativo",IF(AND(M100>#REF!,Cartera!O100="Dólares americanos"),"Rendimiento significativo","Rendimiento no significativo")) -> #REF! | O100: Guaraníes | P100: 6100000 | Q100: =IF(O100="Guaraníes",P100,P100*#REF!) -> 6100000 | R100: =IF(O100="Guaraníes",P100/#REF!,P100) -> #REF! | S100: Pendiente | AC100: =IF(ISNUMBER(SEARCH("Acciones",L100)),"Acciones",IF(ISNUMBER(SEARCH("Bono",L100)),"Bonos",IF(ISNUMBER(SEARCH("CDA",L100)),"CDA",IF(ISNUMBER(SEARCH("Fondo",L100)),"Fondo",0)))) -> Acciones | AD100: Otros | AE100: =IFERROR((MONTH(J100)),0) -> 0 | AF100: =IFERROR((YEAR(J100)),0) -> 0
...
